{"name": "batch_mnhi_richfield_ver01", "url": "http://chroniclingamerica.loc.gov/batches/batch_mnhi_richfield_ver01.json", "page_count": 5944, "awardee": {"url": "http://chroniclingamerica.loc.gov/awardees/mnhi.json", "name": "Minnesota Historical Society; Saint Paul, MN"}, "lccns": ["sn90059523", "sn83045366"], "ingested": "2013-07-08T22:38:48-04:00", "issues": [{"url": "http://chroniclingamerica.loc.gov/lccn/sn83045366/1901-01-01/ed-1.json", "date_issued": "1901-01-01", "title": {"url": "http://chroniclingamerica.loc.gov/lccn/sn83045366.json", "name": "The Minneapolis journal."}}, {"url": "http://chroniclingamerica.loc.gov/lccn/sn83045366/1901-01-02/ed-1.json", "date_issued": "1901-01-02", "title": {"url": "http://chroniclingamerica.loc.gov/lccn/sn83045366.json", "name": "The Minneapolis journal."}}, {"url": "http://chroniclingamerica.loc.gov/lccn/sn83045366/1901-01-03/ed-1.json", "date_issued": "1901-01-03", "title": {"url": "http://chroniclingamerica.loc.gov/lccn/sn83045366.json", "name": "The Minneapolis journal."}}, {"url": "http://chroniclingamerica.loc.gov/lccn/sn83045366/1901-01-04/ed-1.json", "date_issued": "1901-01-04", "title": {"url": "http://chroniclingamerica.loc.gov/lccn/sn83045366.json", "name": "The Minneapolis journal."}}, {"url": "http://chroniclingamerica.loc.gov/lccn/sn83045366/1901-01-05/ed-1.json", "date_issued": "1901-01-05", "title": {"url": "http://chroniclingamerica.loc.gov/lccn/sn83045366.json", "name": "The Minneapolis journal."}}, {"url": "http://chroniclingamerica.loc.gov/lccn/sn83045366/1901-01-07/ed-1.json", "date_issued": "1901-01-07", "title": {"url": "http://chroniclingamerica.loc.gov/lccn/sn83045366.json", "name": "The Minneapolis journal."}}, {"url": "http://chroniclingamerica.loc.gov/lccn/sn83045366/1901-01-08/ed-1.json", "date_issued": "1901-01-08", "title": {"url": "http://chroniclingamerica.loc.gov/lccn/sn83045366.json", "name": "The Minneapolis journal."}}, {"url": "http://chroniclingamerica.loc.gov/lccn/sn83045366/1901-01-09/ed-1.json", "date_issued": "1901-01-09", "title": {"url": "http://chroniclingamerica.loc.gov/lccn/sn83045366.json", "name": "The Minneapolis journal."}}, {"url": "http://chroniclingamerica.loc.gov/lccn/sn83045366/1901-01-10/ed-1.json", "date_issued": "1901-01-10", "title": {"url": "http://chroniclingamerica.loc.gov/lccn/sn83045366.json", "name": "The Minneapolis journal."}}, {"url": "http://chroniclingamerica.loc.gov/lccn/sn83045366/1901-01-11/ed-1.json", "date_issued": "1901-01-11", "title": {"url": "http://chroniclingamerica.loc.gov/lccn/sn83045366.json", "name": "The Minneapolis journal."}}, {"url": "http://chroniclingamerica.loc.gov/lccn/sn83045366/1901-01-12/ed-1.json", "date_issued": "1901-01-12", "title": {"url": "http://chroniclingamerica.loc.gov/lccn/sn83045366.json", "name": "The Minneapolis journal."}}, {"url": "http://chroniclingamerica.loc.gov/lccn/sn83045366/1901-01-14/ed-1.json", "date_issued": "1901-01-14", "title": {"url": "http://chroniclingamerica.loc.gov/lccn/sn83045366.json", "name": "The Minneapolis journal."}}, {"url": "http://chroniclingamerica.loc.gov/lccn/sn83045366/1901-01-15/ed-1.json", "date_issued": "1901-01-15", "title": {"url": "http://chroniclingamerica.loc.gov/lccn/sn83045366.json", "name": "The Minneapolis journal."}}, {"url": "http://chroniclingamerica.loc.gov/lccn/sn83045366/1901-01-16/ed-1.json", "date_issued": "1901-01-16", "title": {"url": "http://chroniclingamerica.loc.gov/lccn/sn83045366.json", "name": "The Minneapolis journal."}}, {"url": "http://chroniclingamerica.loc.gov/lccn/sn83045366/1901-01-17/ed-1.json", "date_issued": "1901-01-17", "title": {"url": "http://chroniclingamerica.loc.gov/lccn/sn83045366.json", "name": "The Minneapolis journal."}}, {"url": "http://chroniclingamerica.loc.gov/lccn/sn83045366/1901-01-18/ed-1.json", "date_issued": "1901-01-18", "title": {"url": "http://chroniclingamerica.loc.gov/lccn/sn83045366.json", "name": "The Minneapolis journal."}}, {"url": "http://chroniclingamerica.loc.gov/lccn/sn83045366/1901-01-19/ed-1.json", "date_issued": "1901-01-19", "title": {"url": "http://chroniclingamerica.loc.gov/lccn/sn83045366.json", "name": "The Minneapolis journal."}}, {"url": "http://chroniclingamerica.loc.gov/lccn/sn83045366/1901-01-21/ed-1.json", "date_issued": "1901-01-21", "title": {"url": "http://chroniclingamerica.loc.gov/lccn/sn83045366.json", "name": "The Minneapolis journal."}}, {"url": "http://chroniclingamerica.loc.gov/lccn/sn83045366/1901-01-22/ed-1.json", "date_issued": "1901-01-22", "title": {"url": "http://chroniclingamerica.loc.gov/lccn/sn83045366.json", "name": "The Minneapolis journal."}}, {"url": "http://chroniclingamerica.loc.gov/lccn/sn83045366/1901-01-23/ed-1.json", "date_issued": "1901-01-23", "title": {"url": "http://chroniclingamerica.loc.gov/lccn/sn83045366.json", "name": "The Minneapolis journal."}}, {"url": "http://chroniclingamerica.loc.gov/lccn/sn83045366/1901-01-24/ed-1.json", "date_issued": "1901-01-24", "title": {"url": "http://chroniclingamerica.loc.gov/lccn/sn83045366.json", "name": "The Minneapolis journal."}}, {"url": "http://chroniclingamerica.loc.gov/lccn/sn83045366/1901-01-25/ed-1.json", "date_issued": "1901-01-25", "title": {"url": "http://chroniclingamerica.loc.gov/lccn/sn83045366.json", "name": "The Minneapolis journal."}}, {"url": "http://chroniclingamerica.loc.gov/lccn/sn83045366/1901-01-26/ed-1.json", "date_issued": "1901-01-26", "title": {"url": "http://chroniclingamerica.loc.gov/lccn/sn83045366.json", "name": "The Minneapolis journal."}}, {"url": "http://chroniclingamerica.loc.gov/lccn/sn83045366/1901-01-28/ed-1.json", "date_issued": "1901-01-28", "title": {"url": "http://chroniclingamerica.loc.gov/lccn/sn83045366.json", "name": "The Minneapolis journal."}}, {"url": "http://chroniclingamerica.loc.gov/lccn/sn83045366/1901-01-29/ed-1.json", "date_issued": "1901-01-29", "title": {"url": "http://chroniclingamerica.loc.gov/lccn/sn83045366.json", "name": "The Minneapolis journal."}}, {"url": "http://chroniclingamerica.loc.gov/lccn/sn83045366/1901-01-30/ed-1.json", "date_issued": "1901-01-30", "title": {"url": "http://chroniclingamerica.loc.gov/lccn/sn83045366.json", "name": "The Minneapolis journal."}}, {"url": "http://chroniclingamerica.loc.gov/lccn/sn83045366/1901-01-31/ed-1.json", "date_issued": "1901-01-31", "title": {"url": "http://chroniclingamerica.loc.gov/lccn/sn83045366.json", "name": "The Minneapolis journal."}}, {"url": "http://chroniclingamerica.loc.gov/lccn/sn83045366/1901-02-01/ed-1.json", "date_issued": "1901-02-01", "title": {"url": "http://chroniclingamerica.loc.gov/lccn/sn83045366.json", "name": "The Minneapolis journal."}}, {"url": "http://chroniclingamerica.loc.gov/lccn/sn83045366/1901-02-02/ed-1.json", "date_issued": "1901-02-02", "title": {"url": "http://chroniclingamerica.loc.gov/lccn/sn83045366.json", "name": "The Minneapolis journal."}}, {"url": "http://chroniclingamerica.loc.gov/lccn/sn83045366/1901-02-04/ed-1.json", "date_issued": "1901-02-04", "title": {"url": "http://chroniclingamerica.loc.gov/lccn/sn83045366.json", "name": "The Minneapolis journal."}}, {"url": "http://chroniclingamerica.loc.gov/lccn/sn83045366/1901-02-05/ed-1.json", "date_issued": "1901-02-05", "title": {"url": "http://chroniclingamerica.loc.gov/lccn/sn83045366.json", "name": "The Minneapolis journal."}}, {"url": "http://chroniclingamerica.loc.gov/lccn/sn83045366/1901-02-06/ed-1.json", "date_issued": "1901-02-06", "title": {"url": "http://chroniclingamerica.loc.gov/lccn/sn83045366.json", "name": "The Minneapolis journal."}}, {"url": "http://chroniclingamerica.loc.gov/lccn/sn83045366/1901-02-07/ed-1.json", "date_issued": "1901-02-07", "title": {"url": "http://chroniclingamerica.loc.gov/lccn/sn83045366.json", "name": "The Minneapolis journal."}}, {"url": "http://chroniclingamerica.loc.gov/lccn/sn83045366/1901-02-08/ed-1.json", "date_issued": "1901-02-08", "title": {"url": "http://chroniclingamerica.loc.gov/lccn/sn83045366.json", "name": "The Minneapolis journal."}}, {"url": "http://chroniclingamerica.loc.gov/lccn/sn83045366/1901-02-09/ed-1.json", "date_issued": "1901-02-09", "title": {"url": "http://chroniclingamerica.loc.gov/lccn/sn83045366.json", "name": "The Minneapolis journal."}}, {"url": "http://chroniclingamerica.loc.gov/lccn/sn83045366/1901-02-11/ed-1.json", "date_issued": "1901-02-11", "title": {"url": "http://chroniclingamerica.loc.gov/lccn/sn83045366.json", "name": "The Minneapolis journal."}}, {"url": "http://chroniclingamerica.loc.gov/lccn/sn83045366/1901-02-12/ed-1.json", "date_issued": "1901-02-12", "title": {"url": "http://chroniclingamerica.loc.gov/lccn/sn83045366.json", "name": "The Minneapolis journal."}}, {"url": "http://chroniclingamerica.loc.gov/lccn/sn83045366/1901-02-13/ed-1.json", "date_issued": "1901-02-13", "title": {"url": "http://chroniclingamerica.loc.gov/lccn/sn83045366.json", "name": "The Minneapolis journal."}}, {"url": "http://chroniclingamerica.loc.gov/lccn/sn83045366/1901-02-14/ed-1.json", "date_issued": "1901-02-14", "title": {"url": "http://chroniclingamerica.loc.gov/lccn/sn83045366.json", "name": "The Minneapolis journal."}}, {"url": "http://chroniclingamerica.loc.gov/lccn/sn83045366/1901-02-15/ed-1.json", "date_issued": "1901-02-15", "title": {"url": "http://chroniclingamerica.loc.gov/lccn/sn83045366.json", "name": "The Minneapolis journal."}}, {"url": "http://chroniclingamerica.loc.gov/lccn/sn83045366/1901-02-16/ed-1.json", "date_issued": "1901-02-16", "title": {"url": "http://chroniclingamerica.loc.gov/lccn/sn83045366.json", "name": "The Minneapolis journal."}}, {"url": "http://chroniclingamerica.loc.gov/lccn/sn83045366/1901-02-18/ed-1.json", "date_issued": "1901-02-18", "title": {"url": "http://chroniclingamerica.loc.gov/lccn/sn83045366.json", "name": "The Minneapolis journal."}}, {"url": "http://chroniclingamerica.loc.gov/lccn/sn83045366/1901-02-19/ed-1.json", "date_issued": "1901-02-19", "title": {"url": "http://chroniclingamerica.loc.gov/lccn/sn83045366.json", "name": "The Minneapolis journal."}}, {"url": "http://chroniclingamerica.loc.gov/lccn/sn83045366/1901-02-20/ed-1.json", "date_issued": "1901-02-20", "title": {"url": "http://chroniclingamerica.loc.gov/lccn/sn83045366.json", "name": "The Minneapolis journal."}}, {"url": "http://chroniclingamerica.loc.gov/lccn/sn83045366/1901-02-21/ed-1.json", "date_issued": "1901-02-21", "title": {"url": "http://chroniclingamerica.loc.gov/lccn/sn83045366.json", "name": "The Minneapolis journal."}}, {"url": "http://chroniclingamerica.loc.gov/lccn/sn83045366/1901-02-22/ed-1.json", "date_issued": "1901-02-22", "title": {"url": "http://chroniclingamerica.loc.gov/lccn/sn83045366.json", "name": "The Minneapolis journal."}}, {"url": "http://chroniclingamerica.loc.gov/lccn/sn83045366/1901-02-23/ed-1.json", "date_issued": "1901-02-23", "title": {"url": "http://chroniclingamerica.loc.gov/lccn/sn83045366.json", "name": "The Minneapolis journal."}}, {"url": "http://chroniclingamerica.loc.gov/lccn/sn83045366/1901-02-25/ed-1.json", "date_issued": "1901-02-25", "title": {"url": "http://chroniclingamerica.loc.gov/lccn/sn83045366.json", "name": "The Minneapolis journal."}}, {"url": "http://chroniclingamerica.loc.gov/lccn/sn83045366/1901-02-26/ed-1.json", "date_issued": "1901-02-26", "title": {"url": "http://chroniclingamerica.loc.gov/lccn/sn83045366.json", "name": "The Minneapolis journal."}}, {"url": "http://chroniclingamerica.loc.gov/lccn/sn83045366/1901-02-27/ed-1.json", "date_issued": "1901-02-27", "title": {"url": "http://chroniclingamerica.loc.gov/lccn/sn83045366.json", "name": "The Minneapolis journal."}}, {"url": "http://chroniclingamerica.loc.gov/lccn/sn83045366/1901-02-28/ed-1.json", "date_issued": "1901-02-28", "title": {"url": "http://chroniclingamerica.loc.gov/lccn/sn83045366.json", "name": "The Minneapolis journal."}}, {"url": "http://chroniclingamerica.loc.gov/lccn/sn83045366/1901-03-01/ed-1.json", "date_issued": "1901-03-01", "title": {"url": "http://chroniclingamerica.loc.gov/lccn/sn83045366.json", "name": "The Minneapolis journal."}}, {"url": "http://chroniclingamerica.loc.gov/lccn/sn83045366/1901-03-02/ed-1.json", "date_issued": "1901-03-02", "title": {"url": "http://chroniclingamerica.loc.gov/lccn/sn83045366.json", "name": "The Minneapolis journal."}}, {"url": "http://chroniclingamerica.loc.gov/lccn/sn83045366/1901-03-04/ed-1.json", "date_issued": "1901-03-04", "title": {"url": "http://chroniclingamerica.loc.gov/lccn/sn83045366.json", "name": "The Minneapolis journal."}}, {"url": "http://chroniclingamerica.loc.gov/lccn/sn83045366/1901-03-05/ed-1.json", "date_issued": "1901-03-05", "title": {"url": "http://chroniclingamerica.loc.gov/lccn/sn83045366.json", "name": "The Minneapolis journal."}}, {"url": "http://chroniclingamerica.loc.gov/lccn/sn83045366/1901-03-06/ed-1.json", "date_issued": "1901-03-06", "title": {"url": "http://chroniclingamerica.loc.gov/lccn/sn83045366.json", "name": "The Minneapolis journal."}}, {"url": "http://chroniclingamerica.loc.gov/lccn/sn83045366/1901-03-07/ed-1.json", "date_issued": "1901-03-07", "title": {"url": "http://chroniclingamerica.loc.gov/lccn/sn83045366.json", "name": "The Minneapolis journal."}}, {"url": "http://chroniclingamerica.loc.gov/lccn/sn83045366/1901-03-08/ed-1.json", "date_issued": "1901-03-08", "title": {"url": "http://chroniclingamerica.loc.gov/lccn/sn83045366.json", "name": "The Minneapolis journal."}}, {"url": "http://chroniclingamerica.loc.gov/lccn/sn83045366/1901-03-09/ed-1.json", "date_issued": "1901-03-09", "title": {"url": "http://chroniclingamerica.loc.gov/lccn/sn83045366.json", "name": "The Minneapolis journal."}}, {"url": "http://chroniclingamerica.loc.gov/lccn/sn83045366/1901-03-11/ed-1.json", "date_issued": "1901-03-11", "title": {"url": "http://chroniclingamerica.loc.gov/lccn/sn83045366.json", "name": "The Minneapolis journal."}}, {"url": "http://chroniclingamerica.loc.gov/lccn/sn83045366/1901-03-12/ed-1.json", "date_issued": "1901-03-12", "title": {"url": "http://chroniclingamerica.loc.gov/lccn/sn83045366.json", "name": "The Minneapolis journal."}}, {"url": "http://chroniclingamerica.loc.gov/lccn/sn83045366/1901-03-13/ed-1.json", "date_issued": "1901-03-13", "title": {"url": "http://chroniclingamerica.loc.gov/lccn/sn83045366.json", "name": "The Minneapolis journal."}}, {"url": "http://chroniclingamerica.loc.gov/lccn/sn83045366/1901-03-14/ed-1.json", "date_issued": "1901-03-14", "title": {"url": "http://chroniclingamerica.loc.gov/lccn/sn83045366.json", "name": "The Minneapolis journal."}}, {"url": "http://chroniclingamerica.loc.gov/lccn/sn83045366/1901-03-15/ed-1.json", "date_issued": "1901-03-15", "title": {"url": "http://chroniclingamerica.loc.gov/lccn/sn83045366.json", "name": "The Minneapolis journal."}}, {"url": "http://chroniclingamerica.loc.gov/lccn/sn83045366/1901-03-16/ed-1.json", "date_issued": "1901-03-16", "title": {"url": "http://chroniclingamerica.loc.gov/lccn/sn83045366.json", "name": "The Minneapolis journal."}}, {"url": "http://chroniclingamerica.loc.gov/lccn/sn83045366/1901-03-18/ed-1.json", "date_issued": "1901-03-18", "title": {"url": "http://chroniclingamerica.loc.gov/lccn/sn83045366.json", "name": "The Minneapolis journal."}}, {"url": "http://chroniclingamerica.loc.gov/lccn/sn83045366/1901-03-19/ed-1.json", "date_issued": "1901-03-19", "title": {"url": "http://chroniclingamerica.loc.gov/lccn/sn83045366.json", "name": "The Minneapolis journal."}}, {"url": "http://chroniclingamerica.loc.gov/lccn/sn83045366/1901-03-20/ed-1.json", "date_issued": "1901-03-20", "title": {"url": "http://chroniclingamerica.loc.gov/lccn/sn83045366.json", "name": "The Minneapolis journal."}}, {"url": "http://chroniclingamerica.loc.gov/lccn/sn83045366/1901-03-21/ed-1.json", "date_issued": "1901-03-21", "title": {"url": "http://chroniclingamerica.loc.gov/lccn/sn83045366.json", "name": "The Minneapolis journal."}}, {"url": "http://chroniclingamerica.loc.gov/lccn/sn83045366/1901-03-22/ed-1.json", "date_issued": "1901-03-22", "title": {"url": "http://chroniclingamerica.loc.gov/lccn/sn83045366.json", "name": "The Minneapolis journal."}}, {"url": "http://chroniclingamerica.loc.gov/lccn/sn83045366/1901-03-23/ed-1.json", "date_issued": "1901-03-23", "title": {"url": "http://chroniclingamerica.loc.gov/lccn/sn83045366.json", "name": "The Minneapolis journal."}}, {"url": "http://chroniclingamerica.loc.gov/lccn/sn83045366/1901-03-25/ed-1.json", "date_issued": "1901-03-25", "title": {"url": "http://chroniclingamerica.loc.gov/lccn/sn83045366.json", "name": "The Minneapolis journal."}}, {"url": "http://chroniclingamerica.loc.gov/lccn/sn83045366/1901-03-26/ed-1.json", "date_issued": "1901-03-26", "title": {"url": "http://chroniclingamerica.loc.gov/lccn/sn83045366.json", "name": "The Minneapolis journal."}}, {"url": "http://chroniclingamerica.loc.gov/lccn/sn83045366/1901-03-27/ed-1.json", "date_issued": "1901-03-27", "title": {"url": "http://chroniclingamerica.loc.gov/lccn/sn83045366.json", "name": "The Minneapolis journal."}}, {"url": "http://chroniclingamerica.loc.gov/lccn/sn83045366/1901-03-28/ed-1.json", "date_issued": "1901-03-28", "title": {"url": "http://chroniclingamerica.loc.gov/lccn/sn83045366.json", "name": "The Minneapolis journal."}}, {"url": "http://chroniclingamerica.loc.gov/lccn/sn83045366/1901-03-29/ed-1.json", "date_issued": "1901-03-29", "title": {"url": "http://chroniclingamerica.loc.gov/lccn/sn83045366.json", "name": "The Minneapolis journal."}}, {"url": "http://chroniclingamerica.loc.gov/lccn/sn83045366/1901-03-30/ed-1.json", "date_issued": "1901-03-30", "title": {"url": "http://chroniclingamerica.loc.gov/lccn/sn83045366.json", "name": "The Minneapolis journal."}}, {"url": "http://chroniclingamerica.loc.gov/lccn/sn83045366/1901-04-01/ed-1.json", "date_issued": "1901-04-01", "title": {"url": "http://chroniclingamerica.loc.gov/lccn/sn83045366.json", "name": "The Minneapolis journal."}}, {"url": "http://chroniclingamerica.loc.gov/lccn/sn83045366/1901-04-02/ed-1.json", "date_issued": "1901-04-02", "title": {"url": "http://chroniclingamerica.loc.gov/lccn/sn83045366.json", "name": "The Minneapolis journal."}}, {"url": "http://chroniclingamerica.loc.gov/lccn/sn83045366/1901-04-03/ed-1.json", "date_issued": "1901-04-03", "title": {"url": "http://chroniclingamerica.loc.gov/lccn/sn83045366.json", "name": "The Minneapolis journal."}}, {"url": "http://chroniclingamerica.loc.gov/lccn/sn83045366/1901-04-04/ed-1.json", "date_issued": "1901-04-04", "title": {"url": "http://chroniclingamerica.loc.gov/lccn/sn83045366.json", "name": "The Minneapolis journal."}}, {"url": "http://chroniclingamerica.loc.gov/lccn/sn83045366/1901-04-05/ed-1.json", "date_issued": "1901-04-05", "title": {"url": "http://chroniclingamerica.loc.gov/lccn/sn83045366.json", "name": "The Minneapolis journal."}}, {"url": "http://chroniclingamerica.loc.gov/lccn/sn83045366/1901-04-06/ed-1.json", "date_issued": "1901-04-06", "title": {"url": "http://chroniclingamerica.loc.gov/lccn/sn83045366.json", "name": "The Minneapolis journal."}}, {"url": "http://chroniclingamerica.loc.gov/lccn/sn83045366/1901-04-08/ed-1.json", "date_issued": "1901-04-08", "title": {"url": "http://chroniclingamerica.loc.gov/lccn/sn83045366.json", "name": "The Minneapolis journal."}}, {"url": "http://chroniclingamerica.loc.gov/lccn/sn83045366/1901-04-09/ed-1.json", "date_issued": "1901-04-09", "title": {"url": "http://chroniclingamerica.loc.gov/lccn/sn83045366.json", "name": "The Minneapolis journal."}}, {"url": "http://chroniclingamerica.loc.gov/lccn/sn83045366/1901-04-10/ed-1.json", "date_issued": "1901-04-10", "title": {"url": "http://chroniclingamerica.loc.gov/lccn/sn83045366.json", "name": "The Minneapolis journal."}}, {"url": "http://chroniclingamerica.loc.gov/lccn/sn83045366/1901-04-11/ed-1.json", "date_issued": "1901-04-11", "title": {"url": "http://chroniclingamerica.loc.gov/lccn/sn83045366.json", "name": "The Minneapolis journal."}}, {"url": "http://chroniclingamerica.loc.gov/lccn/sn83045366/1901-04-12/ed-1.json", "date_issued": "1901-04-12", "title": {"url": "http://chroniclingamerica.loc.gov/lccn/sn83045366.json", "name": "The Minneapolis journal."}}, {"url": "http://chroniclingamerica.loc.gov/lccn/sn83045366/1901-04-13/ed-1.json", "date_issued": "1901-04-13", "title": {"url": "http://chroniclingamerica.loc.gov/lccn/sn83045366.json", "name": "The Minneapolis journal."}}, {"url": "http://chroniclingamerica.loc.gov/lccn/sn83045366/1901-04-15/ed-1.json", "date_issued": "1901-04-15", "title": {"url": "http://chroniclingamerica.loc.gov/lccn/sn83045366.json", "name": "The Minneapolis journal."}}, {"url": "http://chroniclingamerica.loc.gov/lccn/sn83045366/1901-04-16/ed-1.json", "date_issued": "1901-04-16", "title": {"url": "http://chroniclingamerica.loc.gov/lccn/sn83045366.json", "name": "The Minneapolis journal."}}, {"url": "http://chroniclingamerica.loc.gov/lccn/sn83045366/1901-04-17/ed-1.json", "date_issued": "1901-04-17", "title": {"url": "http://chroniclingamerica.loc.gov/lccn/sn83045366.json", "name": "The Minneapolis journal."}}, {"url": "http://chroniclingamerica.loc.gov/lccn/sn83045366/1901-04-18/ed-1.json", "date_issued": "1901-04-18", "title": {"url": "http://chroniclingamerica.loc.gov/lccn/sn83045366.json", "name": "The Minneapolis journal."}}, {"url": "http://chroniclingamerica.loc.gov/lccn/sn83045366/1901-04-19/ed-1.json", "date_issued": "1901-04-19", "title": {"url": "http://chroniclingamerica.loc.gov/lccn/sn83045366.json", "name": "The Minneapolis journal."}}, {"url": "http://chroniclingamerica.loc.gov/lccn/sn83045366/1901-04-20/ed-1.json", "date_issued": "1901-04-20", "title": {"url": "http://chroniclingamerica.loc.gov/lccn/sn83045366.json", "name": "The Minneapolis journal."}}, {"url": "http://chroniclingamerica.loc.gov/lccn/sn83045366/1901-04-22/ed-1.json", "date_issued": "1901-04-22", "title": {"url": "http://chroniclingamerica.loc.gov/lccn/sn83045366.json", "name": "The Minneapolis journal."}}, {"url": "http://chroniclingamerica.loc.gov/lccn/sn83045366/1901-04-23/ed-1.json", "date_issued": "1901-04-23", "title": {"url": "http://chroniclingamerica.loc.gov/lccn/sn83045366.json", "name": "The Minneapolis journal."}}, {"url": "http://chroniclingamerica.loc.gov/lccn/sn83045366/1901-04-24/ed-1.json", "date_issued": "1901-04-24", "title": {"url": "http://chroniclingamerica.loc.gov/lccn/sn83045366.json", "name": "The Minneapolis journal."}}, {"url": "http://chroniclingamerica.loc.gov/lccn/sn83045366/1901-04-25/ed-1.json", "date_issued": "1901-04-25", "title": {"url": "http://chroniclingamerica.loc.gov/lccn/sn83045366.json", "name": "The Minneapolis journal."}}, {"url": "http://chroniclingamerica.loc.gov/lccn/sn83045366/1901-04-26/ed-1.json", "date_issued": "1901-04-26", "title": {"url": "http://chroniclingamerica.loc.gov/lccn/sn83045366.json", "name": "The Minneapolis journal."}}, {"url": "http://chroniclingamerica.loc.gov/lccn/sn83045366/1901-04-27/ed-1.json", "date_issued": "1901-04-27", "title": {"url": "http://chroniclingamerica.loc.gov/lccn/sn83045366.json", "name": "The Minneapolis journal."}}, {"url": "http://chroniclingamerica.loc.gov/lccn/sn83045366/1901-04-29/ed-1.json", "date_issued": "1901-04-29", "title": {"url": "http://chroniclingamerica.loc.gov/lccn/sn83045366.json", "name": "The Minneapolis journal."}}, {"url": "http://chroniclingamerica.loc.gov/lccn/sn83045366/1901-04-30/ed-1.json", "date_issued": "1901-04-30", "title": {"url": "http://chroniclingamerica.loc.gov/lccn/sn83045366.json", "name": "The Minneapolis journal."}}, {"url": "http://chroniclingamerica.loc.gov/lccn/sn90059523/1902-05-01/ed-1.json", "date_issued": "1902-05-01", "title": {"url": "http://chroniclingamerica.loc.gov/lccn/sn90059523.json", "name": "The Saint Paul globe."}}, {"url": "http://chroniclingamerica.loc.gov/lccn/sn90059523/1902-05-02/ed-1.json", "date_issued": "1902-05-02", "title": {"url": "http://chroniclingamerica.loc.gov/lccn/sn90059523.json", "name": "The Saint Paul globe."}}, {"url": "http://chroniclingamerica.loc.gov/lccn/sn90059523/1902-05-03/ed-1.json", "date_issued": "1902-05-03", "title": {"url": "http://chroniclingamerica.loc.gov/lccn/sn90059523.json", "name": "The Saint Paul globe."}}, {"url": "http://chroniclingamerica.loc.gov/lccn/sn90059523/1902-05-04/ed-1.json", "date_issued": "1902-05-04", "title": {"url": "http://chroniclingamerica.loc.gov/lccn/sn90059523.json", "name": "The Saint Paul globe."}}, {"url": "http://chroniclingamerica.loc.gov/lccn/sn90059523/1902-05-05/ed-1.json", "date_issued": "1902-05-05", "title": {"url": "http://chroniclingamerica.loc.gov/lccn/sn90059523.json", "name": "The Saint Paul globe."}}, {"url": "http://chroniclingamerica.loc.gov/lccn/sn90059523/1902-05-06/ed-1.json", "date_issued": "1902-05-06", "title": {"url": "http://chroniclingamerica.loc.gov/lccn/sn90059523.json", "name": "The Saint Paul globe."}}, {"url": "http://chroniclingamerica.loc.gov/lccn/sn90059523/1902-05-07/ed-1.json", "date_issued": "1902-05-07", "title": {"url": "http://chroniclingamerica.loc.gov/lccn/sn90059523.json", "name": "The Saint Paul globe."}}, {"url": "http://chroniclingamerica.loc.gov/lccn/sn90059523/1902-05-08/ed-1.json", "date_issued": "1902-05-08", "title": {"url": "http://chroniclingamerica.loc.gov/lccn/sn90059523.json", "name": "The Saint Paul globe."}}, {"url": "http://chroniclingamerica.loc.gov/lccn/sn90059523/1902-05-09/ed-1.json", "date_issued": "1902-05-09", "title": {"url": "http://chroniclingamerica.loc.gov/lccn/sn90059523.json", "name": "The Saint Paul globe."}}, {"url": "http://chroniclingamerica.loc.gov/lccn/sn90059523/1902-05-10/ed-1.json", "date_issued": "1902-05-10", "title": {"url": "http://chroniclingamerica.loc.gov/lccn/sn90059523.json", "name": "The Saint Paul globe."}}, {"url": "http://chroniclingamerica.loc.gov/lccn/sn90059523/1902-05-11/ed-1.json", "date_issued": "1902-05-11", "title": {"url": "http://chroniclingamerica.loc.gov/lccn/sn90059523.json", "name": "The Saint Paul globe."}}, {"url": "http://chroniclingamerica.loc.gov/lccn/sn90059523/1902-05-12/ed-1.json", "date_issued": "1902-05-12", "title": {"url": "http://chroniclingamerica.loc.gov/lccn/sn90059523.json", "name": "The Saint Paul globe."}}, {"url": "http://chroniclingamerica.loc.gov/lccn/sn90059523/1902-05-13/ed-1.json", "date_issued": "1902-05-13", "title": {"url": "http://chroniclingamerica.loc.gov/lccn/sn90059523.json", "name": "The Saint Paul globe."}}, {"url": "http://chroniclingamerica.loc.gov/lccn/sn90059523/1902-05-14/ed-1.json", "date_issued": "1902-05-14", "title": {"url": "http://chroniclingamerica.loc.gov/lccn/sn90059523.json", "name": "The Saint Paul globe."}}, {"url": "http://chroniclingamerica.loc.gov/lccn/sn90059523/1902-05-15/ed-1.json", "date_issued": "1902-05-15", "title": {"url": "http://chroniclingamerica.loc.gov/lccn/sn90059523.json", "name": "The Saint Paul globe."}}, {"url": "http://chroniclingamerica.loc.gov/lccn/sn90059523/1902-05-16/ed-1.json", "date_issued": "1902-05-16", "title": {"url": "http://chroniclingamerica.loc.gov/lccn/sn90059523.json", "name": "The Saint Paul globe."}}, {"url": "http://chroniclingamerica.loc.gov/lccn/sn90059523/1902-05-17/ed-1.json", "date_issued": "1902-05-17", "title": {"url": "http://chroniclingamerica.loc.gov/lccn/sn90059523.json", "name": "The Saint Paul globe."}}, {"url": "http://chroniclingamerica.loc.gov/lccn/sn90059523/1902-05-18/ed-1.json", "date_issued": "1902-05-18", "title": {"url": "http://chroniclingamerica.loc.gov/lccn/sn90059523.json", "name": "The Saint Paul globe."}}, {"url": "http://chroniclingamerica.loc.gov/lccn/sn90059523/1902-05-19/ed-1.json", "date_issued": "1902-05-19", "title": {"url": "http://chroniclingamerica.loc.gov/lccn/sn90059523.json", "name": "The Saint Paul globe."}}, {"url": "http://chroniclingamerica.loc.gov/lccn/sn90059523/1902-05-20/ed-1.json", "date_issued": "1902-05-20", "title": {"url": "http://chroniclingamerica.loc.gov/lccn/sn90059523.json", "name": "The Saint Paul globe."}}, {"url": "http://chroniclingamerica.loc.gov/lccn/sn90059523/1902-05-21/ed-1.json", "date_issued": "1902-05-21", "title": {"url": "http://chroniclingamerica.loc.gov/lccn/sn90059523.json", "name": "The Saint Paul globe."}}, {"url": "http://chroniclingamerica.loc.gov/lccn/sn90059523/1902-05-22/ed-1.json", "date_issued": "1902-05-22", "title": {"url": "http://chroniclingamerica.loc.gov/lccn/sn90059523.json", "name": "The Saint Paul globe."}}, {"url": "http://chroniclingamerica.loc.gov/lccn/sn90059523/1902-05-23/ed-1.json", "date_issued": "1902-05-23", "title": {"url": "http://chroniclingamerica.loc.gov/lccn/sn90059523.json", "name": "The Saint Paul globe."}}, {"url": "http://chroniclingamerica.loc.gov/lccn/sn90059523/1902-05-24/ed-1.json", "date_issued": "1902-05-24", "title": {"url": "http://chroniclingamerica.loc.gov/lccn/sn90059523.json", "name": "The Saint Paul globe."}}, {"url": "http://chroniclingamerica.loc.gov/lccn/sn90059523/1902-05-25/ed-1.json", "date_issued": "1902-05-25", "title": {"url": "http://chroniclingamerica.loc.gov/lccn/sn90059523.json", "name": "The Saint Paul globe."}}, {"url": "http://chroniclingamerica.loc.gov/lccn/sn90059523/1902-05-26/ed-1.json", "date_issued": "1902-05-26", "title": {"url": "http://chroniclingamerica.loc.gov/lccn/sn90059523.json", "name": "The Saint Paul globe."}}, {"url": "http://chroniclingamerica.loc.gov/lccn/sn90059523/1902-05-27/ed-1.json", "date_issued": "1902-05-27", "title": {"url": "http://chroniclingamerica.loc.gov/lccn/sn90059523.json", "name": "The Saint Paul globe."}}, {"url": "http://chroniclingamerica.loc.gov/lccn/sn90059523/1902-05-28/ed-1.json", "date_issued": "1902-05-28", "title": {"url": "http://chroniclingamerica.loc.gov/lccn/sn90059523.json", "name": "The Saint Paul globe."}}, {"url": "http://chroniclingamerica.loc.gov/lccn/sn90059523/1902-05-29/ed-1.json", "date_issued": "1902-05-29", "title": {"url": "http://chroniclingamerica.loc.gov/lccn/sn90059523.json", "name": "The Saint Paul globe."}}, {"url": "http://chroniclingamerica.loc.gov/lccn/sn90059523/1902-05-30/ed-1.json", "date_issued": "1902-05-30", "title": {"url": "http://chroniclingamerica.loc.gov/lccn/sn90059523.json", "name": "The Saint Paul globe."}}, {"url": "http://chroniclingamerica.loc.gov/lccn/sn90059523/1902-05-31/ed-1.json", "date_issued": "1902-05-31", "title": {"url": "http://chroniclingamerica.loc.gov/lccn/sn90059523.json", "name": "The Saint Paul globe."}}, {"url": "http://chroniclingamerica.loc.gov/lccn/sn90059523/1902-06-01/ed-1.json", "date_issued": "1902-06-01", "title": {"url": "http://chroniclingamerica.loc.gov/lccn/sn90059523.json", "name": "The Saint Paul globe."}}, {"url": "http://chroniclingamerica.loc.gov/lccn/sn90059523/1902-06-02/ed-1.json", "date_issued": "1902-06-02", "title": {"url": "http://chroniclingamerica.loc.gov/lccn/sn90059523.json", "name": "The Saint Paul globe."}}, {"url": "http://chroniclingamerica.loc.gov/lccn/sn90059523/1902-06-03/ed-1.json", "date_issued": "1902-06-03", "title": {"url": "http://chroniclingamerica.loc.gov/lccn/sn90059523.json", "name": "The Saint Paul globe."}}, {"url": "http://chroniclingamerica.loc.gov/lccn/sn90059523/1902-06-04/ed-1.json", "date_issued": "1902-06-04", "title": {"url": "http://chroniclingamerica.loc.gov/lccn/sn90059523.json", "name": "The Saint Paul globe."}}, {"url": "http://chroniclingamerica.loc.gov/lccn/sn90059523/1902-06-05/ed-1.json", "date_issued": "1902-06-05", "title": {"url": "http://chroniclingamerica.loc.gov/lccn/sn90059523.json", "name": "The Saint Paul globe."}}, {"url": "http://chroniclingamerica.loc.gov/lccn/sn90059523/1902-06-06/ed-1.json", "date_issued": "1902-06-06", "title": {"url": "http://chroniclingamerica.loc.gov/lccn/sn90059523.json", "name": "The Saint Paul globe."}}, {"url": "http://chroniclingamerica.loc.gov/lccn/sn90059523/1902-06-07/ed-1.json", "date_issued": "1902-06-07", "title": {"url": "http://chroniclingamerica.loc.gov/lccn/sn90059523.json", "name": "The Saint Paul globe."}}, {"url": "http://chroniclingamerica.loc.gov/lccn/sn90059523/1902-06-08/ed-1.json", "date_issued": "1902-06-08", "title": {"url": "http://chroniclingamerica.loc.gov/lccn/sn90059523.json", "name": "The Saint Paul globe."}}, {"url": "http://chroniclingamerica.loc.gov/lccn/sn90059523/1902-06-09/ed-1.json", "date_issued": "1902-06-09", "title": {"url": "http://chroniclingamerica.loc.gov/lccn/sn90059523.json", "name": "The Saint Paul globe."}}, {"url": "http://chroniclingamerica.loc.gov/lccn/sn90059523/1902-06-10/ed-1.json", "date_issued": "1902-06-10", "title": {"url": "http://chroniclingamerica.loc.gov/lccn/sn90059523.json", "name": "The Saint Paul globe."}}, {"url": "http://chroniclingamerica.loc.gov/lccn/sn90059523/1902-06-11/ed-1.json", "date_issued": "1902-06-11", "title": {"url": "http://chroniclingamerica.loc.gov/lccn/sn90059523.json", "name": "The Saint Paul globe."}}, {"url": "http://chroniclingamerica.loc.gov/lccn/sn90059523/1902-06-12/ed-1.json", "date_issued": "1902-06-12", "title": {"url": "http://chroniclingamerica.loc.gov/lccn/sn90059523.json", "name": "The Saint Paul globe."}}, {"url": "http://chroniclingamerica.loc.gov/lccn/sn90059523/1902-06-13/ed-1.json", "date_issued": "1902-06-13", "title": {"url": "http://chroniclingamerica.loc.gov/lccn/sn90059523.json", "name": "The Saint Paul globe."}}, {"url": "http://chroniclingamerica.loc.gov/lccn/sn90059523/1902-06-14/ed-1.json", "date_issued": "1902-06-14", "title": {"url": "http://chroniclingamerica.loc.gov/lccn/sn90059523.json", "name": "The Saint Paul globe."}}, {"url": "http://chroniclingamerica.loc.gov/lccn/sn90059523/1902-06-15/ed-1.json", "date_issued": "1902-06-15", "title": {"url": "http://chroniclingamerica.loc.gov/lccn/sn90059523.json", "name": "The Saint Paul globe."}}, {"url": "http://chroniclingamerica.loc.gov/lccn/sn90059523/1902-06-16/ed-1.json", "date_issued": "1902-06-16", "title": {"url": "http://chroniclingamerica.loc.gov/lccn/sn90059523.json", "name": "The Saint Paul globe."}}, {"url": "http://chroniclingamerica.loc.gov/lccn/sn90059523/1902-06-17/ed-1.json", "date_issued": "1902-06-17", "title": {"url": "http://chroniclingamerica.loc.gov/lccn/sn90059523.json", "name": "The Saint Paul globe."}}, {"url": "http://chroniclingamerica.loc.gov/lccn/sn90059523/1902-06-18/ed-1.json", "date_issued": "1902-06-18", "title": {"url": "http://chroniclingamerica.loc.gov/lccn/sn90059523.json", "name": "The Saint Paul globe."}}, {"url": "http://chroniclingamerica.loc.gov/lccn/sn90059523/1902-06-19/ed-1.json", "date_issued": "1902-06-19", "title": {"url": "http://chroniclingamerica.loc.gov/lccn/sn90059523.json", "name": "The Saint Paul globe."}}, {"url": "http://chroniclingamerica.loc.gov/lccn/sn90059523/1902-06-20/ed-1.json", "date_issued": "1902-06-20", "title": {"url": "http://chroniclingamerica.loc.gov/lccn/sn90059523.json", "name": "The Saint Paul globe."}}, {"url": "http://chroniclingamerica.loc.gov/lccn/sn90059523/1902-06-21/ed-1.json", "date_issued": "1902-06-21", "title": {"url": "http://chroniclingamerica.loc.gov/lccn/sn90059523.json", "name": "The Saint Paul globe."}}, {"url": "http://chroniclingamerica.loc.gov/lccn/sn90059523/1902-06-22/ed-1.json", "date_issued": "1902-06-22", "title": {"url": "http://chroniclingamerica.loc.gov/lccn/sn90059523.json", "name": "The Saint Paul globe."}}, {"url": "http://chroniclingamerica.loc.gov/lccn/sn90059523/1902-06-23/ed-1.json", "date_issued": "1902-06-23", "title": {"url": "http://chroniclingamerica.loc.gov/lccn/sn90059523.json", "name": "The Saint Paul globe."}}, {"url": "http://chroniclingamerica.loc.gov/lccn/sn90059523/1902-06-24/ed-1.json", "date_issued": "1902-06-24", "title": {"url": "http://chroniclingamerica.loc.gov/lccn/sn90059523.json", "name": "The Saint Paul globe."}}, {"url": "http://chroniclingamerica.loc.gov/lccn/sn90059523/1902-06-25/ed-1.json", "date_issued": "1902-06-25", "title": {"url": "http://chroniclingamerica.loc.gov/lccn/sn90059523.json", "name": "The Saint Paul globe."}}, {"url": "http://chroniclingamerica.loc.gov/lccn/sn90059523/1902-06-26/ed-1.json", "date_issued": "1902-06-26", "title": {"url": "http://chroniclingamerica.loc.gov/lccn/sn90059523.json", "name": "The Saint Paul globe."}}, {"url": "http://chroniclingamerica.loc.gov/lccn/sn90059523/1902-06-27/ed-1.json", "date_issued": "1902-06-27", "title": {"url": "http://chroniclingamerica.loc.gov/lccn/sn90059523.json", "name": "The Saint Paul globe."}}, {"url": "http://chroniclingamerica.loc.gov/lccn/sn90059523/1902-06-28/ed-1.json", "date_issued": "1902-06-28", "title": {"url": "http://chroniclingamerica.loc.gov/lccn/sn90059523.json", "name": "The Saint Paul globe."}}, {"url": "http://chroniclingamerica.loc.gov/lccn/sn90059523/1902-06-29/ed-1.json", "date_issued": "1902-06-29", "title": {"url": "http://chroniclingamerica.loc.gov/lccn/sn90059523.json", "name": "The Saint Paul globe."}}, {"url": "http://chroniclingamerica.loc.gov/lccn/sn90059523/1902-06-30/ed-1.json", "date_issued": "1902-06-30", "title": {"url": "http://chroniclingamerica.loc.gov/lccn/sn90059523.json", "name": "The Saint Paul globe."}}, {"url": "http://chroniclingamerica.loc.gov/lccn/sn90059523/1902-11-01/ed-1.json", "date_issued": "1902-11-01", "title": {"url": "http://chroniclingamerica.loc.gov/lccn/sn90059523.json", "name": "The Saint Paul globe."}}, {"url": "http://chroniclingamerica.loc.gov/lccn/sn90059523/1902-11-02/ed-1.json", "date_issued": "1902-11-02", "title": {"url": "http://chroniclingamerica.loc.gov/lccn/sn90059523.json", "name": "The Saint Paul globe."}}, {"url": "http://chroniclingamerica.loc.gov/lccn/sn90059523/1902-11-03/ed-1.json", "date_issued": "1902-11-03", "title": {"url": "http://chroniclingamerica.loc.gov/lccn/sn90059523.json", "name": "The Saint Paul globe."}}, {"url": "http://chroniclingamerica.loc.gov/lccn/sn90059523/1902-11-04/ed-1.json", "date_issued": "1902-11-04", "title": {"url": "http://chroniclingamerica.loc.gov/lccn/sn90059523.json", "name": "The Saint Paul globe."}}, {"url": "http://chroniclingamerica.loc.gov/lccn/sn90059523/1902-11-05/ed-1.json", "date_issued": "1902-11-05", "title": {"url": "http://chroniclingamerica.loc.gov/lccn/sn90059523.json", "name": "The Saint Paul globe."}}, {"url": "http://chroniclingamerica.loc.gov/lccn/sn90059523/1902-11-06/ed-1.json", "date_issued": "1902-11-06", "title": {"url": "http://chroniclingamerica.loc.gov/lccn/sn90059523.json", "name": "The Saint Paul globe."}}, {"url": "http://chroniclingamerica.loc.gov/lccn/sn90059523/1902-11-07/ed-1.json", "date_issued": "1902-11-07", "title": {"url": "http://chroniclingamerica.loc.gov/lccn/sn90059523.json", "name": "The Saint Paul globe."}}, {"url": "http://chroniclingamerica.loc.gov/lccn/sn90059523/1902-11-08/ed-1.json", "date_issued": "1902-11-08", "title": {"url": "http://chroniclingamerica.loc.gov/lccn/sn90059523.json", "name": "The Saint Paul globe."}}, {"url": "http://chroniclingamerica.loc.gov/lccn/sn90059523/1902-11-09/ed-1.json", "date_issued": "1902-11-09", "title": {"url": "http://chroniclingamerica.loc.gov/lccn/sn90059523.json", "name": "The Saint Paul globe."}}, {"url": "http://chroniclingamerica.loc.gov/lccn/sn90059523/1902-11-10/ed-1.json", "date_issued": "1902-11-10", "title": {"url": "http://chroniclingamerica.loc.gov/lccn/sn90059523.json", "name": "The Saint Paul globe."}}, {"url": "http://chroniclingamerica.loc.gov/lccn/sn90059523/1902-11-11/ed-1.json", "date_issued": "1902-11-11", "title": {"url": "http://chroniclingamerica.loc.gov/lccn/sn90059523.json", "name": "The Saint Paul globe."}}, {"url": "http://chroniclingamerica.loc.gov/lccn/sn90059523/1902-11-12/ed-1.json", "date_issued": "1902-11-12", "title": {"url": "http://chroniclingamerica.loc.gov/lccn/sn90059523.json", "name": "The Saint Paul globe."}}, {"url": "http://chroniclingamerica.loc.gov/lccn/sn90059523/1902-11-13/ed-1.json", "date_issued": "1902-11-13", "title": {"url": "http://chroniclingamerica.loc.gov/lccn/sn90059523.json", "name": "The Saint Paul globe."}}, {"url": "http://chroniclingamerica.loc.gov/lccn/sn90059523/1902-11-14/ed-1.json", "date_issued": "1902-11-14", "title": {"url": "http://chroniclingamerica.loc.gov/lccn/sn90059523.json", "name": "The Saint Paul globe."}}, {"url": "http://chroniclingamerica.loc.gov/lccn/sn90059523/1902-11-15/ed-1.json", "date_issued": "1902-11-15", "title": {"url": "http://chroniclingamerica.loc.gov/lccn/sn90059523.json", "name": "The Saint Paul globe."}}, {"url": "http://chroniclingamerica.loc.gov/lccn/sn90059523/1902-11-16/ed-1.json", "date_issued": "1902-11-16", "title": {"url": "http://chroniclingamerica.loc.gov/lccn/sn90059523.json", "name": "The Saint Paul globe."}}, {"url": "http://chroniclingamerica.loc.gov/lccn/sn90059523/1902-11-17/ed-1.json", "date_issued": "1902-11-17", "title": {"url": "http://chroniclingamerica.loc.gov/lccn/sn90059523.json", "name": "The Saint Paul globe."}}, {"url": "http://chroniclingamerica.loc.gov/lccn/sn90059523/1902-11-18/ed-1.json", "date_issued": "1902-11-18", "title": {"url": "http://chroniclingamerica.loc.gov/lccn/sn90059523.json", "name": "The Saint Paul globe."}}, {"url": "http://chroniclingamerica.loc.gov/lccn/sn90059523/1902-11-19/ed-1.json", "date_issued": "1902-11-19", "title": {"url": "http://chroniclingamerica.loc.gov/lccn/sn90059523.json", "name": "The Saint Paul globe."}}, {"url": "http://chroniclingamerica.loc.gov/lccn/sn90059523/1902-11-20/ed-1.json", "date_issued": "1902-11-20", "title": {"url": "http://chroniclingamerica.loc.gov/lccn/sn90059523.json", "name": "The Saint Paul globe."}}, {"url": "http://chroniclingamerica.loc.gov/lccn/sn90059523/1902-11-21/ed-1.json", "date_issued": "1902-11-21", "title": {"url": "http://chroniclingamerica.loc.gov/lccn/sn90059523.json", "name": "The Saint Paul globe."}}, {"url": "http://chroniclingamerica.loc.gov/lccn/sn90059523/1902-11-22/ed-1.json", "date_issued": "1902-11-22", "title": {"url": "http://chroniclingamerica.loc.gov/lccn/sn90059523.json", "name": "The Saint Paul globe."}}, {"url": "http://chroniclingamerica.loc.gov/lccn/sn90059523/1902-11-23/ed-1.json", "date_issued": "1902-11-23", "title": {"url": "http://chroniclingamerica.loc.gov/lccn/sn90059523.json", "name": "The Saint Paul globe."}}, {"url": "http://chroniclingamerica.loc.gov/lccn/sn90059523/1902-11-24/ed-1.json", "date_issued": "1902-11-24", "title": {"url": "http://chroniclingamerica.loc.gov/lccn/sn90059523.json", "name": "The Saint Paul globe."}}, {"url": "http://chroniclingamerica.loc.gov/lccn/sn90059523/1902-11-25/ed-1.json", "date_issued": "1902-11-25", "title": {"url": "http://chroniclingamerica.loc.gov/lccn/sn90059523.json", "name": "The Saint Paul globe."}}, {"url": "http://chroniclingamerica.loc.gov/lccn/sn90059523/1902-11-26/ed-1.json", "date_issued": "1902-11-26", "title": {"url": "http://chroniclingamerica.loc.gov/lccn/sn90059523.json", "name": "The Saint Paul globe."}}, {"url": "http://chroniclingamerica.loc.gov/lccn/sn90059523/1902-11-27/ed-1.json", "date_issued": "1902-11-27", "title": {"url": "http://chroniclingamerica.loc.gov/lccn/sn90059523.json", "name": "The Saint Paul globe."}}, {"url": "http://chroniclingamerica.loc.gov/lccn/sn90059523/1902-11-28/ed-1.json", "date_issued": "1902-11-28", "title": {"url": "http://chroniclingamerica.loc.gov/lccn/sn90059523.json", "name": "The Saint Paul globe."}}, {"url": "http://chroniclingamerica.loc.gov/lccn/sn90059523/1902-11-29/ed-1.json", "date_issued": "1902-11-29", "title": {"url": "http://chroniclingamerica.loc.gov/lccn/sn90059523.json", "name": "The Saint Paul globe."}}, {"url": "http://chroniclingamerica.loc.gov/lccn/sn90059523/1902-11-30/ed-1.json", "date_issued": "1902-11-30", "title": {"url": "http://chroniclingamerica.loc.gov/lccn/sn90059523.json", "name": "The Saint Paul globe."}}, {"url": "http://chroniclingamerica.loc.gov/lccn/sn90059523/1902-12-01/ed-1.json", "date_issued": "1902-12-01", "title": {"url": "http://chroniclingamerica.loc.gov/lccn/sn90059523.json", "name": "The Saint Paul globe."}}, {"url": "http://chroniclingamerica.loc.gov/lccn/sn90059523/1902-12-02/ed-1.json", "date_issued": "1902-12-02", "title": {"url": "http://chroniclingamerica.loc.gov/lccn/sn90059523.json", "name": "The Saint Paul globe."}}, {"url": "http://chroniclingamerica.loc.gov/lccn/sn90059523/1902-12-03/ed-1.json", "date_issued": "1902-12-03", "title": {"url": "http://chroniclingamerica.loc.gov/lccn/sn90059523.json", "name": "The Saint Paul globe."}}, {"url": "http://chroniclingamerica.loc.gov/lccn/sn90059523/1902-12-04/ed-1.json", "date_issued": "1902-12-04", "title": {"url": "http://chroniclingamerica.loc.gov/lccn/sn90059523.json", "name": "The Saint Paul globe."}}, {"url": "http://chroniclingamerica.loc.gov/lccn/sn90059523/1902-12-05/ed-1.json", "date_issued": "1902-12-05", "title": {"url": "http://chroniclingamerica.loc.gov/lccn/sn90059523.json", "name": "The Saint Paul globe."}}, {"url": "http://chroniclingamerica.loc.gov/lccn/sn90059523/1902-12-06/ed-1.json", "date_issued": "1902-12-06", "title": {"url": "http://chroniclingamerica.loc.gov/lccn/sn90059523.json", "name": "The Saint Paul globe."}}, {"url": "http://chroniclingamerica.loc.gov/lccn/sn90059523/1902-12-07/ed-1.json", "date_issued": "1902-12-07", "title": {"url": "http://chroniclingamerica.loc.gov/lccn/sn90059523.json", "name": "The Saint Paul globe."}}, {"url": "http://chroniclingamerica.loc.gov/lccn/sn90059523/1902-12-08/ed-1.json", "date_issued": "1902-12-08", "title": {"url": "http://chroniclingamerica.loc.gov/lccn/sn90059523.json", "name": "The Saint Paul globe."}}, {"url": "http://chroniclingamerica.loc.gov/lccn/sn90059523/1902-12-09/ed-1.json", "date_issued": "1902-12-09", "title": {"url": "http://chroniclingamerica.loc.gov/lccn/sn90059523.json", "name": "The Saint Paul globe."}}, {"url": "http://chroniclingamerica.loc.gov/lccn/sn90059523/1902-12-10/ed-1.json", "date_issued": "1902-12-10", "title": {"url": "http://chroniclingamerica.loc.gov/lccn/sn90059523.json", "name": "The Saint Paul globe."}}, {"url": "http://chroniclingamerica.loc.gov/lccn/sn90059523/1902-12-11/ed-1.json", "date_issued": "1902-12-11", "title": {"url": "http://chroniclingamerica.loc.gov/lccn/sn90059523.json", "name": "The Saint Paul globe."}}, {"url": "http://chroniclingamerica.loc.gov/lccn/sn90059523/1902-12-12/ed-1.json", "date_issued": "1902-12-12", "title": {"url": "http://chroniclingamerica.loc.gov/lccn/sn90059523.json", "name": "The Saint Paul globe."}}, {"url": "http://chroniclingamerica.loc.gov/lccn/sn90059523/1902-12-13/ed-1.json", "date_issued": "1902-12-13", "title": {"url": "http://chroniclingamerica.loc.gov/lccn/sn90059523.json", "name": "The Saint Paul globe."}}, {"url": "http://chroniclingamerica.loc.gov/lccn/sn90059523/1902-12-14/ed-1.json", "date_issued": "1902-12-14", "title": {"url": "http://chroniclingamerica.loc.gov/lccn/sn90059523.json", "name": "The Saint Paul globe."}}, {"url": "http://chroniclingamerica.loc.gov/lccn/sn90059523/1902-12-15/ed-1.json", "date_issued": "1902-12-15", "title": {"url": "http://chroniclingamerica.loc.gov/lccn/sn90059523.json", "name": "The Saint Paul globe."}}, {"url": "http://chroniclingamerica.loc.gov/lccn/sn90059523/1902-12-16/ed-1.json", "date_issued": "1902-12-16", "title": {"url": "http://chroniclingamerica.loc.gov/lccn/sn90059523.json", "name": "The Saint Paul globe."}}, {"url": "http://chroniclingamerica.loc.gov/lccn/sn90059523/1902-12-17/ed-1.json", "date_issued": "1902-12-17", "title": {"url": "http://chroniclingamerica.loc.gov/lccn/sn90059523.json", "name": "The Saint Paul globe."}}, {"url": "http://chroniclingamerica.loc.gov/lccn/sn90059523/1902-12-18/ed-1.json", "date_issued": "1902-12-18", "title": {"url": "http://chroniclingamerica.loc.gov/lccn/sn90059523.json", "name": "The Saint Paul globe."}}, {"url": "http://chroniclingamerica.loc.gov/lccn/sn90059523/1902-12-19/ed-1.json", "date_issued": "1902-12-19", "title": {"url": "http://chroniclingamerica.loc.gov/lccn/sn90059523.json", "name": "The Saint Paul globe."}}, {"url": "http://chroniclingamerica.loc.gov/lccn/sn90059523/1902-12-20/ed-1.json", "date_issued": "1902-12-20", "title": {"url": "http://chroniclingamerica.loc.gov/lccn/sn90059523.json", "name": "The Saint Paul globe."}}, {"url": "http://chroniclingamerica.loc.gov/lccn/sn90059523/1902-12-21/ed-1.json", "date_issued": "1902-12-21", "title": {"url": "http://chroniclingamerica.loc.gov/lccn/sn90059523.json", "name": "The Saint Paul globe."}}, {"url": "http://chroniclingamerica.loc.gov/lccn/sn90059523/1902-12-22/ed-1.json", "date_issued": "1902-12-22", "title": {"url": "http://chroniclingamerica.loc.gov/lccn/sn90059523.json", "name": "The Saint Paul globe."}}, {"url": "http://chroniclingamerica.loc.gov/lccn/sn90059523/1902-12-23/ed-1.json", "date_issued": "1902-12-23", "title": {"url": "http://chroniclingamerica.loc.gov/lccn/sn90059523.json", "name": "The Saint Paul globe."}}, {"url": "http://chroniclingamerica.loc.gov/lccn/sn90059523/1902-12-24/ed-1.json", "date_issued": "1902-12-24", "title": {"url": "http://chroniclingamerica.loc.gov/lccn/sn90059523.json", "name": "The Saint Paul globe."}}, {"url": "http://chroniclingamerica.loc.gov/lccn/sn90059523/1902-12-25/ed-1.json", "date_issued": "1902-12-25", "title": {"url": "http://chroniclingamerica.loc.gov/lccn/sn90059523.json", "name": "The Saint Paul globe."}}, {"url": "http://chroniclingamerica.loc.gov/lccn/sn90059523/1902-12-26/ed-1.json", "date_issued": "1902-12-26", "title": {"url": "http://chroniclingamerica.loc.gov/lccn/sn90059523.json", "name": "The Saint Paul globe."}}, {"url": "http://chroniclingamerica.loc.gov/lccn/sn90059523/1902-12-27/ed-1.json", "date_issued": "1902-12-27", "title": {"url": "http://chroniclingamerica.loc.gov/lccn/sn90059523.json", "name": "The Saint Paul globe."}}, {"url": "http://chroniclingamerica.loc.gov/lccn/sn90059523/1902-12-28/ed-1.json", "date_issued": "1902-12-28", "title": {"url": "http://chroniclingamerica.loc.gov/lccn/sn90059523.json", "name": "The Saint Paul globe."}}, {"url": "http://chroniclingamerica.loc.gov/lccn/sn90059523/1902-12-29/ed-1.json", "date_issued": "1902-12-29", "title": {"url": "http://chroniclingamerica.loc.gov/lccn/sn90059523.json", "name": "The Saint Paul globe."}}, {"url": "http://chroniclingamerica.loc.gov/lccn/sn90059523/1902-12-30/ed-1.json", "date_issued": "1902-12-30", "title": {"url": "http://chroniclingamerica.loc.gov/lccn/sn90059523.json", "name": "The Saint Paul globe."}}, {"url": "http://chroniclingamerica.loc.gov/lccn/sn90059523/1902-12-31/ed-1.json", "date_issued": "1902-12-31", "title": {"url": "http://chroniclingamerica.loc.gov/lccn/sn90059523.json", "name": "The Saint Paul globe."}}, {"url": "http://chroniclingamerica.loc.gov/lccn/sn90059523/1903-05-01/ed-1.json", "date_issued": "1903-05-01", "title": {"url": "http://chroniclingamerica.loc.gov/lccn/sn90059523.json", "name": "The Saint Paul globe."}}, {"url": "http://chroniclingamerica.loc.gov/lccn/sn90059523/1903-05-02/ed-1.json", "date_issued": "1903-05-02", "title": {"url": "http://chroniclingamerica.loc.gov/lccn/sn90059523.json", "name": "The Saint Paul globe."}}, {"url": "http://chroniclingamerica.loc.gov/lccn/sn90059523/1903-05-03/ed-1.json", "date_issued": "1903-05-03", "title": {"url": "http://chroniclingamerica.loc.gov/lccn/sn90059523.json", "name": "The Saint Paul globe."}}, {"url": "http://chroniclingamerica.loc.gov/lccn/sn90059523/1903-05-04/ed-1.json", "date_issued": "1903-05-04", "title": {"url": "http://chroniclingamerica.loc.gov/lccn/sn90059523.json", "name": "The Saint Paul globe."}}, {"url": "http://chroniclingamerica.loc.gov/lccn/sn90059523/1903-05-05/ed-1.json", "date_issued": "1903-05-05", "title": {"url": "http://chroniclingamerica.loc.gov/lccn/sn90059523.json", "name": "The Saint Paul globe."}}, {"url": "http://chroniclingamerica.loc.gov/lccn/sn90059523/1903-05-06/ed-1.json", "date_issued": "1903-05-06", "title": {"url": "http://chroniclingamerica.loc.gov/lccn/sn90059523.json", "name": "The Saint Paul globe."}}, {"url": "http://chroniclingamerica.loc.gov/lccn/sn90059523/1903-05-07/ed-1.json", "date_issued": "1903-05-07", "title": {"url": "http://chroniclingamerica.loc.gov/lccn/sn90059523.json", "name": "The Saint Paul globe."}}, {"url": "http://chroniclingamerica.loc.gov/lccn/sn90059523/1903-05-08/ed-1.json", "date_issued": "1903-05-08", "title": {"url": "http://chroniclingamerica.loc.gov/lccn/sn90059523.json", "name": "The Saint Paul globe."}}, {"url": "http://chroniclingamerica.loc.gov/lccn/sn90059523/1903-05-09/ed-1.json", "date_issued": "1903-05-09", "title": {"url": "http://chroniclingamerica.loc.gov/lccn/sn90059523.json", "name": "The Saint Paul globe."}}, {"url": "http://chroniclingamerica.loc.gov/lccn/sn90059523/1903-05-10/ed-1.json", "date_issued": "1903-05-10", "title": {"url": "http://chroniclingamerica.loc.gov/lccn/sn90059523.json", "name": "The Saint Paul globe."}}, {"url": "http://chroniclingamerica.loc.gov/lccn/sn90059523/1903-05-11/ed-1.json", "date_issued": "1903-05-11", "title": {"url": "http://chroniclingamerica.loc.gov/lccn/sn90059523.json", "name": "The Saint Paul globe."}}, {"url": "http://chroniclingamerica.loc.gov/lccn/sn90059523/1903-05-12/ed-1.json", "date_issued": "1903-05-12", "title": {"url": "http://chroniclingamerica.loc.gov/lccn/sn90059523.json", "name": "The Saint Paul globe."}}, {"url": "http://chroniclingamerica.loc.gov/lccn/sn90059523/1903-05-13/ed-1.json", "date_issued": "1903-05-13", "title": {"url": "http://chroniclingamerica.loc.gov/lccn/sn90059523.json", "name": "The Saint Paul globe."}}, {"url": "http://chroniclingamerica.loc.gov/lccn/sn90059523/1903-05-14/ed-1.json", "date_issued": "1903-05-14", "title": {"url": "http://chroniclingamerica.loc.gov/lccn/sn90059523.json", "name": "The Saint Paul globe."}}, {"url": "http://chroniclingamerica.loc.gov/lccn/sn90059523/1903-05-15/ed-1.json", "date_issued": "1903-05-15", "title": {"url": "http://chroniclingamerica.loc.gov/lccn/sn90059523.json", "name": "The Saint Paul globe."}}, {"url": "http://chroniclingamerica.loc.gov/lccn/sn90059523/1903-05-16/ed-1.json", "date_issued": "1903-05-16", "title": {"url": "http://chroniclingamerica.loc.gov/lccn/sn90059523.json", "name": "The Saint Paul globe."}}, {"url": "http://chroniclingamerica.loc.gov/lccn/sn90059523/1903-05-17/ed-1.json", "date_issued": "1903-05-17", "title": {"url": "http://chroniclingamerica.loc.gov/lccn/sn90059523.json", "name": "The Saint Paul globe."}}, {"url": "http://chroniclingamerica.loc.gov/lccn/sn90059523/1903-05-18/ed-1.json", "date_issued": "1903-05-18", "title": {"url": "http://chroniclingamerica.loc.gov/lccn/sn90059523.json", "name": "The Saint Paul globe."}}, {"url": "http://chroniclingamerica.loc.gov/lccn/sn90059523/1903-05-19/ed-1.json", "date_issued": "1903-05-19", "title": {"url": "http://chroniclingamerica.loc.gov/lccn/sn90059523.json", "name": "The Saint Paul globe."}}, {"url": "http://chroniclingamerica.loc.gov/lccn/sn90059523/1903-05-20/ed-1.json", "date_issued": "1903-05-20", "title": {"url": "http://chroniclingamerica.loc.gov/lccn/sn90059523.json", "name": "The Saint Paul globe."}}, {"url": "http://chroniclingamerica.loc.gov/lccn/sn90059523/1903-05-21/ed-1.json", "date_issued": "1903-05-21", "title": {"url": "http://chroniclingamerica.loc.gov/lccn/sn90059523.json", "name": "The Saint Paul globe."}}, {"url": "http://chroniclingamerica.loc.gov/lccn/sn90059523/1903-05-22/ed-1.json", "date_issued": "1903-05-22", "title": {"url": "http://chroniclingamerica.loc.gov/lccn/sn90059523.json", "name": "The Saint Paul globe."}}, {"url": "http://chroniclingamerica.loc.gov/lccn/sn90059523/1903-05-23/ed-1.json", "date_issued": "1903-05-23", "title": {"url": "http://chroniclingamerica.loc.gov/lccn/sn90059523.json", "name": "The Saint Paul globe."}}, {"url": "http://chroniclingamerica.loc.gov/lccn/sn90059523/1903-05-24/ed-1.json", "date_issued": "1903-05-24", "title": {"url": "http://chroniclingamerica.loc.gov/lccn/sn90059523.json", "name": "The Saint Paul globe."}}, {"url": "http://chroniclingamerica.loc.gov/lccn/sn90059523/1903-05-25/ed-1.json", "date_issued": "1903-05-25", "title": {"url": "http://chroniclingamerica.loc.gov/lccn/sn90059523.json", "name": "The Saint Paul globe."}}, {"url": "http://chroniclingamerica.loc.gov/lccn/sn90059523/1903-05-26/ed-1.json", "date_issued": "1903-05-26", "title": {"url": "http://chroniclingamerica.loc.gov/lccn/sn90059523.json", "name": "The Saint Paul globe."}}, {"url": "http://chroniclingamerica.loc.gov/lccn/sn90059523/1903-05-27/ed-1.json", "date_issued": "1903-05-27", "title": {"url": "http://chroniclingamerica.loc.gov/lccn/sn90059523.json", "name": "The Saint Paul globe."}}, {"url": "http://chroniclingamerica.loc.gov/lccn/sn90059523/1903-05-28/ed-1.json", "date_issued": "1903-05-28", "title": {"url": "http://chroniclingamerica.loc.gov/lccn/sn90059523.json", "name": "The Saint Paul globe."}}, {"url": "http://chroniclingamerica.loc.gov/lccn/sn90059523/1903-05-29/ed-1.json", "date_issued": "1903-05-29", "title": {"url": "http://chroniclingamerica.loc.gov/lccn/sn90059523.json", "name": "The Saint Paul globe."}}, {"url": "http://chroniclingamerica.loc.gov/lccn/sn90059523/1903-05-30/ed-1.json", "date_issued": "1903-05-30", "title": {"url": "http://chroniclingamerica.loc.gov/lccn/sn90059523.json", "name": "The Saint Paul globe."}}, {"url": "http://chroniclingamerica.loc.gov/lccn/sn90059523/1903-05-31/ed-1.json", "date_issued": "1903-05-31", "title": {"url": "http://chroniclingamerica.loc.gov/lccn/sn90059523.json", "name": "The Saint Paul globe."}}, {"url": "http://chroniclingamerica.loc.gov/lccn/sn90059523/1903-12-01/ed-1.json", "date_issued": "1903-12-01", "title": {"url": "http://chroniclingamerica.loc.gov/lccn/sn90059523.json", "name": "The Saint Paul globe."}}, {"url": "http://chroniclingamerica.loc.gov/lccn/sn90059523/1903-12-02/ed-1.json", "date_issued": "1903-12-02", "title": {"url": "http://chroniclingamerica.loc.gov/lccn/sn90059523.json", "name": "The Saint Paul globe."}}, {"url": "http://chroniclingamerica.loc.gov/lccn/sn90059523/1903-12-03/ed-1.json", "date_issued": "1903-12-03", "title": {"url": "http://chroniclingamerica.loc.gov/lccn/sn90059523.json", "name": "The Saint Paul globe."}}, {"url": "http://chroniclingamerica.loc.gov/lccn/sn90059523/1903-12-04/ed-1.json", "date_issued": "1903-12-04", "title": {"url": "http://chroniclingamerica.loc.gov/lccn/sn90059523.json", "name": "The Saint Paul globe."}}, {"url": "http://chroniclingamerica.loc.gov/lccn/sn90059523/1903-12-05/ed-1.json", "date_issued": "1903-12-05", "title": {"url": "http://chroniclingamerica.loc.gov/lccn/sn90059523.json", "name": "The Saint Paul globe."}}, {"url": "http://chroniclingamerica.loc.gov/lccn/sn90059523/1903-12-06/ed-1.json", "date_issued": "1903-12-06", "title": {"url": "http://chroniclingamerica.loc.gov/lccn/sn90059523.json", "name": "The Saint Paul globe."}}, {"url": "http://chroniclingamerica.loc.gov/lccn/sn90059523/1903-12-07/ed-1.json", "date_issued": "1903-12-07", "title": {"url": "http://chroniclingamerica.loc.gov/lccn/sn90059523.json", "name": "The Saint Paul globe."}}, {"url": "http://chroniclingamerica.loc.gov/lccn/sn90059523/1903-12-08/ed-1.json", "date_issued": "1903-12-08", "title": {"url": "http://chroniclingamerica.loc.gov/lccn/sn90059523.json", "name": "The Saint Paul globe."}}, {"url": "http://chroniclingamerica.loc.gov/lccn/sn90059523/1903-12-09/ed-1.json", "date_issued": "1903-12-09", "title": {"url": "http://chroniclingamerica.loc.gov/lccn/sn90059523.json", "name": "The Saint Paul globe."}}, {"url": "http://chroniclingamerica.loc.gov/lccn/sn90059523/1903-12-10/ed-1.json", "date_issued": "1903-12-10", "title": {"url": "http://chroniclingamerica.loc.gov/lccn/sn90059523.json", "name": "The Saint Paul globe."}}, {"url": "http://chroniclingamerica.loc.gov/lccn/sn90059523/1903-12-11/ed-1.json", "date_issued": "1903-12-11", "title": {"url": "http://chroniclingamerica.loc.gov/lccn/sn90059523.json", "name": "The Saint Paul globe."}}, {"url": "http://chroniclingamerica.loc.gov/lccn/sn90059523/1903-12-12/ed-1.json", "date_issued": "1903-12-12", "title": {"url": "http://chroniclingamerica.loc.gov/lccn/sn90059523.json", "name": "The Saint Paul globe."}}, {"url": "http://chroniclingamerica.loc.gov/lccn/sn90059523/1903-12-13/ed-1.json", "date_issued": "1903-12-13", "title": {"url": "http://chroniclingamerica.loc.gov/lccn/sn90059523.json", "name": "The Saint Paul globe."}}, {"url": "http://chroniclingamerica.loc.gov/lccn/sn90059523/1903-12-14/ed-1.json", "date_issued": "1903-12-14", "title": {"url": "http://chroniclingamerica.loc.gov/lccn/sn90059523.json", "name": "The Saint Paul globe."}}, {"url": "http://chroniclingamerica.loc.gov/lccn/sn90059523/1903-12-15/ed-1.json", "date_issued": "1903-12-15", "title": {"url": "http://chroniclingamerica.loc.gov/lccn/sn90059523.json", "name": "The Saint Paul globe."}}, {"url": "http://chroniclingamerica.loc.gov/lccn/sn90059523/1903-12-16/ed-1.json", "date_issued": "1903-12-16", "title": {"url": "http://chroniclingamerica.loc.gov/lccn/sn90059523.json", "name": "The Saint Paul globe."}}, {"url": "http://chroniclingamerica.loc.gov/lccn/sn90059523/1903-12-17/ed-1.json", "date_issued": "1903-12-17", "title": {"url": "http://chroniclingamerica.loc.gov/lccn/sn90059523.json", "name": "The Saint Paul globe."}}, {"url": "http://chroniclingamerica.loc.gov/lccn/sn90059523/1903-12-18/ed-1.json", "date_issued": "1903-12-18", "title": {"url": "http://chroniclingamerica.loc.gov/lccn/sn90059523.json", "name": "The Saint Paul globe."}}, {"url": "http://chroniclingamerica.loc.gov/lccn/sn90059523/1903-12-19/ed-1.json", "date_issued": "1903-12-19", "title": {"url": "http://chroniclingamerica.loc.gov/lccn/sn90059523.json", "name": "The Saint Paul globe."}}, {"url": "http://chroniclingamerica.loc.gov/lccn/sn90059523/1903-12-20/ed-1.json", "date_issued": "1903-12-20", "title": {"url": "http://chroniclingamerica.loc.gov/lccn/sn90059523.json", "name": "The Saint Paul globe."}}, {"url": "http://chroniclingamerica.loc.gov/lccn/sn90059523/1903-12-21/ed-1.json", "date_issued": "1903-12-21", "title": {"url": "http://chroniclingamerica.loc.gov/lccn/sn90059523.json", "name": "The Saint Paul globe."}}, {"url": "http://chroniclingamerica.loc.gov/lccn/sn90059523/1903-12-22/ed-1.json", "date_issued": "1903-12-22", "title": {"url": "http://chroniclingamerica.loc.gov/lccn/sn90059523.json", "name": "The Saint Paul globe."}}, {"url": "http://chroniclingamerica.loc.gov/lccn/sn90059523/1903-12-23/ed-1.json", "date_issued": "1903-12-23", "title": {"url": "http://chroniclingamerica.loc.gov/lccn/sn90059523.json", "name": "The Saint Paul globe."}}, {"url": "http://chroniclingamerica.loc.gov/lccn/sn90059523/1903-12-24/ed-1.json", "date_issued": "1903-12-24", "title": {"url": "http://chroniclingamerica.loc.gov/lccn/sn90059523.json", "name": "The Saint Paul globe."}}, {"url": "http://chroniclingamerica.loc.gov/lccn/sn90059523/1903-12-25/ed-1.json", "date_issued": "1903-12-25", "title": {"url": "http://chroniclingamerica.loc.gov/lccn/sn90059523.json", "name": "The Saint Paul globe."}}, {"url": "http://chroniclingamerica.loc.gov/lccn/sn90059523/1903-12-26/ed-1.json", "date_issued": "1903-12-26", "title": {"url": "http://chroniclingamerica.loc.gov/lccn/sn90059523.json", "name": "The Saint Paul globe."}}, {"url": "http://chroniclingamerica.loc.gov/lccn/sn90059523/1903-12-27/ed-1.json", "date_issued": "1903-12-27", "title": {"url": "http://chroniclingamerica.loc.gov/lccn/sn90059523.json", "name": "The Saint Paul globe."}}, {"url": "http://chroniclingamerica.loc.gov/lccn/sn90059523/1903-12-28/ed-1.json", "date_issued": "1903-12-28", "title": {"url": "http://chroniclingamerica.loc.gov/lccn/sn90059523.json", "name": "The Saint Paul globe."}}, {"url": "http://chroniclingamerica.loc.gov/lccn/sn90059523/1903-12-29/ed-1.json", "date_issued": "1903-12-29", "title": {"url": "http://chroniclingamerica.loc.gov/lccn/sn90059523.json", "name": "The Saint Paul globe."}}, {"url": "http://chroniclingamerica.loc.gov/lccn/sn90059523/1903-12-30/ed-1.json", "date_issued": "1903-12-30", "title": {"url": "http://chroniclingamerica.loc.gov/lccn/sn90059523.json", "name": "The Saint Paul globe."}}, {"url": "http://chroniclingamerica.loc.gov/lccn/sn90059523/1903-12-31/ed-1.json", "date_issued": "1903-12-31", "title": {"url": "http://chroniclingamerica.loc.gov/lccn/sn90059523.json", "name": "The Saint Paul globe."}}, {"url": "http://chroniclingamerica.loc.gov/lccn/sn90059523/1904-08-01/ed-1.json", "date_issued": "1904-08-01", "title": {"url": "http://chroniclingamerica.loc.gov/lccn/sn90059523.json", "name": "The Saint Paul globe."}}, {"url": "http://chroniclingamerica.loc.gov/lccn/sn90059523/1904-08-02/ed-1.json", "date_issued": "1904-08-02", "title": {"url": "http://chroniclingamerica.loc.gov/lccn/sn90059523.json", "name": "The Saint Paul globe."}}, {"url": "http://chroniclingamerica.loc.gov/lccn/sn90059523/1904-08-03/ed-1.json", "date_issued": "1904-08-03", "title": {"url": "http://chroniclingamerica.loc.gov/lccn/sn90059523.json", "name": "The Saint Paul globe."}}, {"url": "http://chroniclingamerica.loc.gov/lccn/sn90059523/1904-08-04/ed-1.json", "date_issued": "1904-08-04", "title": {"url": "http://chroniclingamerica.loc.gov/lccn/sn90059523.json", "name": "The Saint Paul globe."}}, {"url": "http://chroniclingamerica.loc.gov/lccn/sn90059523/1904-08-05/ed-1.json", "date_issued": "1904-08-05", "title": {"url": "http://chroniclingamerica.loc.gov/lccn/sn90059523.json", "name": "The Saint Paul globe."}}, {"url": "http://chroniclingamerica.loc.gov/lccn/sn90059523/1904-08-06/ed-1.json", "date_issued": "1904-08-06", "title": {"url": "http://chroniclingamerica.loc.gov/lccn/sn90059523.json", "name": "The Saint Paul globe."}}, {"url": "http://chroniclingamerica.loc.gov/lccn/sn90059523/1904-08-07/ed-1.json", "date_issued": "1904-08-07", "title": {"url": "http://chroniclingamerica.loc.gov/lccn/sn90059523.json", "name": "The Saint Paul globe."}}, {"url": "http://chroniclingamerica.loc.gov/lccn/sn90059523/1904-08-08/ed-1.json", "date_issued": "1904-08-08", "title": {"url": "http://chroniclingamerica.loc.gov/lccn/sn90059523.json", "name": "The Saint Paul globe."}}, {"url": "http://chroniclingamerica.loc.gov/lccn/sn90059523/1904-08-09/ed-1.json", "date_issued": "1904-08-09", "title": {"url": "http://chroniclingamerica.loc.gov/lccn/sn90059523.json", "name": "The Saint Paul globe."}}, {"url": "http://chroniclingamerica.loc.gov/lccn/sn90059523/1904-08-10/ed-1.json", "date_issued": "1904-08-10", "title": {"url": "http://chroniclingamerica.loc.gov/lccn/sn90059523.json", "name": "The Saint Paul globe."}}, {"url": "http://chroniclingamerica.loc.gov/lccn/sn90059523/1904-08-11/ed-1.json", "date_issued": "1904-08-11", "title": {"url": "http://chroniclingamerica.loc.gov/lccn/sn90059523.json", "name": "The Saint Paul globe."}}, {"url": "http://chroniclingamerica.loc.gov/lccn/sn90059523/1904-08-12/ed-1.json", "date_issued": "1904-08-12", "title": {"url": "http://chroniclingamerica.loc.gov/lccn/sn90059523.json", "name": "The Saint Paul globe."}}, {"url": "http://chroniclingamerica.loc.gov/lccn/sn90059523/1904-08-13/ed-1.json", "date_issued": "1904-08-13", "title": {"url": "http://chroniclingamerica.loc.gov/lccn/sn90059523.json", "name": "The Saint Paul globe."}}, {"url": "http://chroniclingamerica.loc.gov/lccn/sn90059523/1904-08-14/ed-1.json", "date_issued": "1904-08-14", "title": {"url": "http://chroniclingamerica.loc.gov/lccn/sn90059523.json", "name": "The Saint Paul globe."}}, {"url": "http://chroniclingamerica.loc.gov/lccn/sn90059523/1904-08-15/ed-1.json", "date_issued": "1904-08-15", "title": {"url": "http://chroniclingamerica.loc.gov/lccn/sn90059523.json", "name": "The Saint Paul globe."}}, {"url": "http://chroniclingamerica.loc.gov/lccn/sn90059523/1904-08-16/ed-1.json", "date_issued": "1904-08-16", "title": {"url": "http://chroniclingamerica.loc.gov/lccn/sn90059523.json", "name": "The Saint Paul globe."}}, {"url": "http://chroniclingamerica.loc.gov/lccn/sn90059523/1904-08-17/ed-1.json", "date_issued": "1904-08-17", "title": {"url": "http://chroniclingamerica.loc.gov/lccn/sn90059523.json", "name": "The Saint Paul globe."}}, {"url": "http://chroniclingamerica.loc.gov/lccn/sn90059523/1904-08-18/ed-1.json", "date_issued": "1904-08-18", "title": {"url": "http://chroniclingamerica.loc.gov/lccn/sn90059523.json", "name": "The Saint Paul globe."}}, {"url": "http://chroniclingamerica.loc.gov/lccn/sn90059523/1904-08-19/ed-1.json", "date_issued": "1904-08-19", "title": {"url": "http://chroniclingamerica.loc.gov/lccn/sn90059523.json", "name": "The Saint Paul globe."}}, {"url": "http://chroniclingamerica.loc.gov/lccn/sn90059523/1904-08-20/ed-1.json", "date_issued": "1904-08-20", "title": {"url": "http://chroniclingamerica.loc.gov/lccn/sn90059523.json", "name": "The Saint Paul globe."}}, {"url": "http://chroniclingamerica.loc.gov/lccn/sn90059523/1904-08-21/ed-1.json", "date_issued": "1904-08-21", "title": {"url": "http://chroniclingamerica.loc.gov/lccn/sn90059523.json", "name": "The Saint Paul globe."}}, {"url": "http://chroniclingamerica.loc.gov/lccn/sn90059523/1904-08-22/ed-1.json", "date_issued": "1904-08-22", "title": {"url": "http://chroniclingamerica.loc.gov/lccn/sn90059523.json", "name": "The Saint Paul globe."}}, {"url": "http://chroniclingamerica.loc.gov/lccn/sn90059523/1904-08-23/ed-1.json", "date_issued": "1904-08-23", "title": {"url": "http://chroniclingamerica.loc.gov/lccn/sn90059523.json", "name": "The Saint Paul globe."}}, {"url": "http://chroniclingamerica.loc.gov/lccn/sn90059523/1904-08-24/ed-1.json", "date_issued": "1904-08-24", "title": {"url": "http://chroniclingamerica.loc.gov/lccn/sn90059523.json", "name": "The Saint Paul globe."}}, {"url": "http://chroniclingamerica.loc.gov/lccn/sn90059523/1904-08-25/ed-1.json", "date_issued": "1904-08-25", "title": {"url": "http://chroniclingamerica.loc.gov/lccn/sn90059523.json", "name": "The Saint Paul globe."}}, {"url": "http://chroniclingamerica.loc.gov/lccn/sn90059523/1904-08-26/ed-1.json", "date_issued": "1904-08-26", "title": {"url": "http://chroniclingamerica.loc.gov/lccn/sn90059523.json", "name": "The Saint Paul globe."}}, {"url": "http://chroniclingamerica.loc.gov/lccn/sn90059523/1904-08-27/ed-1.json", "date_issued": "1904-08-27", "title": {"url": "http://chroniclingamerica.loc.gov/lccn/sn90059523.json", "name": "The Saint Paul globe."}}, {"url": "http://chroniclingamerica.loc.gov/lccn/sn90059523/1904-08-28/ed-1.json", "date_issued": "1904-08-28", "title": {"url": "http://chroniclingamerica.loc.gov/lccn/sn90059523.json", "name": "The Saint Paul globe."}}, {"url": "http://chroniclingamerica.loc.gov/lccn/sn90059523/1904-08-29/ed-1.json", "date_issued": "1904-08-29", "title": {"url": "http://chroniclingamerica.loc.gov/lccn/sn90059523.json", "name": "The Saint Paul globe."}}, {"url": "http://chroniclingamerica.loc.gov/lccn/sn90059523/1904-08-30/ed-1.json", "date_issued": "1904-08-30", "title": {"url": "http://chroniclingamerica.loc.gov/lccn/sn90059523.json", "name": "The Saint Paul globe."}}, {"url": "http://chroniclingamerica.loc.gov/lccn/sn90059523/1904-08-31/ed-1.json", "date_issued": "1904-08-31", "title": {"url": "http://chroniclingamerica.loc.gov/lccn/sn90059523.json", "name": "The Saint Paul globe."}}, {"url": "http://chroniclingamerica.loc.gov/lccn/sn90059523/1904-11-01/ed-1.json", "date_issued": "1904-11-01", "title": {"url": "http://chroniclingamerica.loc.gov/lccn/sn90059523.json", "name": "The Saint Paul globe."}}, {"url": "http://chroniclingamerica.loc.gov/lccn/sn90059523/1904-11-02/ed-1.json", "date_issued": "1904-11-02", "title": {"url": "http://chroniclingamerica.loc.gov/lccn/sn90059523.json", "name": "The Saint Paul globe."}}, {"url": "http://chroniclingamerica.loc.gov/lccn/sn90059523/1904-11-03/ed-1.json", "date_issued": "1904-11-03", "title": {"url": "http://chroniclingamerica.loc.gov/lccn/sn90059523.json", "name": "The Saint Paul globe."}}, {"url": "http://chroniclingamerica.loc.gov/lccn/sn90059523/1904-11-04/ed-1.json", "date_issued": "1904-11-04", "title": {"url": "http://chroniclingamerica.loc.gov/lccn/sn90059523.json", "name": "The Saint Paul globe."}}, {"url": "http://chroniclingamerica.loc.gov/lccn/sn90059523/1904-11-05/ed-1.json", "date_issued": "1904-11-05", "title": {"url": "http://chroniclingamerica.loc.gov/lccn/sn90059523.json", "name": "The Saint Paul globe."}}, {"url": "http://chroniclingamerica.loc.gov/lccn/sn90059523/1904-11-06/ed-1.json", "date_issued": "1904-11-06", "title": {"url": "http://chroniclingamerica.loc.gov/lccn/sn90059523.json", "name": "The Saint Paul globe."}}, {"url": "http://chroniclingamerica.loc.gov/lccn/sn90059523/1904-11-07/ed-1.json", "date_issued": "1904-11-07", "title": {"url": "http://chroniclingamerica.loc.gov/lccn/sn90059523.json", "name": "The Saint Paul globe."}}, {"url": "http://chroniclingamerica.loc.gov/lccn/sn90059523/1904-11-08/ed-1.json", "date_issued": "1904-11-08", "title": {"url": "http://chroniclingamerica.loc.gov/lccn/sn90059523.json", "name": "The Saint Paul globe."}}, {"url": "http://chroniclingamerica.loc.gov/lccn/sn90059523/1904-11-09/ed-1.json", "date_issued": "1904-11-09", "title": {"url": "http://chroniclingamerica.loc.gov/lccn/sn90059523.json", "name": "The Saint Paul globe."}}, {"url": "http://chroniclingamerica.loc.gov/lccn/sn90059523/1904-11-10/ed-1.json", "date_issued": "1904-11-10", "title": {"url": "http://chroniclingamerica.loc.gov/lccn/sn90059523.json", "name": "The Saint Paul globe."}}, {"url": "http://chroniclingamerica.loc.gov/lccn/sn90059523/1904-11-11/ed-1.json", "date_issued": "1904-11-11", "title": {"url": "http://chroniclingamerica.loc.gov/lccn/sn90059523.json", "name": "The Saint Paul globe."}}, {"url": "http://chroniclingamerica.loc.gov/lccn/sn90059523/1904-11-12/ed-1.json", "date_issued": "1904-11-12", "title": {"url": "http://chroniclingamerica.loc.gov/lccn/sn90059523.json", "name": "The Saint Paul globe."}}, {"url": "http://chroniclingamerica.loc.gov/lccn/sn90059523/1904-11-13/ed-1.json", "date_issued": "1904-11-13", "title": {"url": "http://chroniclingamerica.loc.gov/lccn/sn90059523.json", "name": "The Saint Paul globe."}}, {"url": "http://chroniclingamerica.loc.gov/lccn/sn90059523/1904-11-14/ed-1.json", "date_issued": "1904-11-14", "title": {"url": "http://chroniclingamerica.loc.gov/lccn/sn90059523.json", "name": "The Saint Paul globe."}}, {"url": "http://chroniclingamerica.loc.gov/lccn/sn90059523/1904-11-15/ed-1.json", "date_issued": "1904-11-15", "title": {"url": "http://chroniclingamerica.loc.gov/lccn/sn90059523.json", "name": "The Saint Paul globe."}}, {"url": "http://chroniclingamerica.loc.gov/lccn/sn90059523/1904-11-16/ed-1.json", "date_issued": "1904-11-16", "title": {"url": "http://chroniclingamerica.loc.gov/lccn/sn90059523.json", "name": "The Saint Paul globe."}}, {"url": "http://chroniclingamerica.loc.gov/lccn/sn90059523/1904-11-17/ed-1.json", "date_issued": "1904-11-17", "title": {"url": "http://chroniclingamerica.loc.gov/lccn/sn90059523.json", "name": "The Saint Paul globe."}}, {"url": "http://chroniclingamerica.loc.gov/lccn/sn90059523/1904-11-18/ed-1.json", "date_issued": "1904-11-18", "title": {"url": "http://chroniclingamerica.loc.gov/lccn/sn90059523.json", "name": "The Saint Paul globe."}}, {"url": "http://chroniclingamerica.loc.gov/lccn/sn90059523/1904-11-19/ed-1.json", "date_issued": "1904-11-19", "title": {"url": "http://chroniclingamerica.loc.gov/lccn/sn90059523.json", "name": "The Saint Paul globe."}}, {"url": "http://chroniclingamerica.loc.gov/lccn/sn90059523/1904-11-20/ed-1.json", "date_issued": "1904-11-20", "title": {"url": "http://chroniclingamerica.loc.gov/lccn/sn90059523.json", "name": "The Saint Paul globe."}}, {"url": "http://chroniclingamerica.loc.gov/lccn/sn90059523/1904-11-21/ed-1.json", "date_issued": "1904-11-21", "title": {"url": "http://chroniclingamerica.loc.gov/lccn/sn90059523.json", "name": "The Saint Paul globe."}}, {"url": "http://chroniclingamerica.loc.gov/lccn/sn90059523/1904-11-22/ed-1.json", "date_issued": "1904-11-22", "title": {"url": "http://chroniclingamerica.loc.gov/lccn/sn90059523.json", "name": "The Saint Paul globe."}}, {"url": "http://chroniclingamerica.loc.gov/lccn/sn90059523/1904-11-23/ed-1.json", "date_issued": "1904-11-23", "title": {"url": "http://chroniclingamerica.loc.gov/lccn/sn90059523.json", "name": "The Saint Paul globe."}}, {"url": "http://chroniclingamerica.loc.gov/lccn/sn90059523/1904-11-24/ed-1.json", "date_issued": "1904-11-24", "title": {"url": "http://chroniclingamerica.loc.gov/lccn/sn90059523.json", "name": "The Saint Paul globe."}}, {"url": "http://chroniclingamerica.loc.gov/lccn/sn90059523/1904-11-25/ed-1.json", "date_issued": "1904-11-25", "title": {"url": "http://chroniclingamerica.loc.gov/lccn/sn90059523.json", "name": "The Saint Paul globe."}}, {"url": "http://chroniclingamerica.loc.gov/lccn/sn90059523/1904-11-26/ed-1.json", "date_issued": "1904-11-26", "title": {"url": "http://chroniclingamerica.loc.gov/lccn/sn90059523.json", "name": "The Saint Paul globe."}}, {"url": "http://chroniclingamerica.loc.gov/lccn/sn90059523/1904-11-27/ed-1.json", "date_issued": "1904-11-27", "title": {"url": "http://chroniclingamerica.loc.gov/lccn/sn90059523.json", "name": "The Saint Paul globe."}}, {"url": "http://chroniclingamerica.loc.gov/lccn/sn90059523/1904-11-28/ed-1.json", "date_issued": "1904-11-28", "title": {"url": "http://chroniclingamerica.loc.gov/lccn/sn90059523.json", "name": "The Saint Paul globe."}}, {"url": "http://chroniclingamerica.loc.gov/lccn/sn90059523/1904-11-29/ed-1.json", "date_issued": "1904-11-29", "title": {"url": "http://chroniclingamerica.loc.gov/lccn/sn90059523.json", "name": "The Saint Paul globe."}}, {"url": "http://chroniclingamerica.loc.gov/lccn/sn90059523/1904-11-30/ed-1.json", "date_issued": "1904-11-30", "title": {"url": "http://chroniclingamerica.loc.gov/lccn/sn90059523.json", "name": "The Saint Paul globe."}}, {"url": "http://chroniclingamerica.loc.gov/lccn/sn90059523/1904-12-01/ed-1.json", "date_issued": "1904-12-01", "title": {"url": "http://chroniclingamerica.loc.gov/lccn/sn90059523.json", "name": "The Saint Paul globe."}}, {"url": "http://chroniclingamerica.loc.gov/lccn/sn90059523/1904-12-02/ed-1.json", "date_issued": "1904-12-02", "title": {"url": "http://chroniclingamerica.loc.gov/lccn/sn90059523.json", "name": "The Saint Paul globe."}}, {"url": "http://chroniclingamerica.loc.gov/lccn/sn90059523/1904-12-03/ed-1.json", "date_issued": "1904-12-03", "title": {"url": "http://chroniclingamerica.loc.gov/lccn/sn90059523.json", "name": "The Saint Paul globe."}}, {"url": "http://chroniclingamerica.loc.gov/lccn/sn90059523/1904-12-04/ed-1.json", "date_issued": "1904-12-04", "title": {"url": "http://chroniclingamerica.loc.gov/lccn/sn90059523.json", "name": "The Saint Paul globe."}}, {"url": "http://chroniclingamerica.loc.gov/lccn/sn90059523/1904-12-05/ed-1.json", "date_issued": "1904-12-05", "title": {"url": "http://chroniclingamerica.loc.gov/lccn/sn90059523.json", "name": "The Saint Paul globe."}}, {"url": "http://chroniclingamerica.loc.gov/lccn/sn90059523/1904-12-06/ed-1.json", "date_issued": "1904-12-06", "title": {"url": "http://chroniclingamerica.loc.gov/lccn/sn90059523.json", "name": "The Saint Paul globe."}}, {"url": "http://chroniclingamerica.loc.gov/lccn/sn90059523/1904-12-07/ed-1.json", "date_issued": "1904-12-07", "title": {"url": "http://chroniclingamerica.loc.gov/lccn/sn90059523.json", "name": "The Saint Paul globe."}}, {"url": "http://chroniclingamerica.loc.gov/lccn/sn90059523/1904-12-08/ed-1.json", "date_issued": "1904-12-08", "title": {"url": "http://chroniclingamerica.loc.gov/lccn/sn90059523.json", "name": "The Saint Paul globe."}}, {"url": "http://chroniclingamerica.loc.gov/lccn/sn90059523/1904-12-09/ed-1.json", "date_issued": "1904-12-09", "title": {"url": "http://chroniclingamerica.loc.gov/lccn/sn90059523.json", "name": "The Saint Paul globe."}}, {"url": "http://chroniclingamerica.loc.gov/lccn/sn90059523/1904-12-10/ed-1.json", "date_issued": "1904-12-10", "title": {"url": "http://chroniclingamerica.loc.gov/lccn/sn90059523.json", "name": "The Saint Paul globe."}}, {"url": "http://chroniclingamerica.loc.gov/lccn/sn90059523/1904-12-11/ed-1.json", "date_issued": "1904-12-11", "title": {"url": "http://chroniclingamerica.loc.gov/lccn/sn90059523.json", "name": "The Saint Paul globe."}}, {"url": "http://chroniclingamerica.loc.gov/lccn/sn90059523/1904-12-12/ed-1.json", "date_issued": "1904-12-12", "title": {"url": "http://chroniclingamerica.loc.gov/lccn/sn90059523.json", "name": "The Saint Paul globe."}}, {"url": "http://chroniclingamerica.loc.gov/lccn/sn90059523/1904-12-13/ed-1.json", "date_issued": "1904-12-13", "title": {"url": "http://chroniclingamerica.loc.gov/lccn/sn90059523.json", "name": "The Saint Paul globe."}}, {"url": "http://chroniclingamerica.loc.gov/lccn/sn90059523/1904-12-14/ed-1.json", "date_issued": "1904-12-14", "title": {"url": "http://chroniclingamerica.loc.gov/lccn/sn90059523.json", "name": "The Saint Paul globe."}}, {"url": "http://chroniclingamerica.loc.gov/lccn/sn90059523/1904-12-15/ed-1.json", "date_issued": "1904-12-15", "title": {"url": "http://chroniclingamerica.loc.gov/lccn/sn90059523.json", "name": "The Saint Paul globe."}}, {"url": "http://chroniclingamerica.loc.gov/lccn/sn90059523/1904-12-16/ed-1.json", "date_issued": "1904-12-16", "title": {"url": "http://chroniclingamerica.loc.gov/lccn/sn90059523.json", "name": "The Saint Paul globe."}}, {"url": "http://chroniclingamerica.loc.gov/lccn/sn90059523/1904-12-17/ed-1.json", "date_issued": "1904-12-17", "title": {"url": "http://chroniclingamerica.loc.gov/lccn/sn90059523.json", "name": "The Saint Paul globe."}}, {"url": "http://chroniclingamerica.loc.gov/lccn/sn90059523/1904-12-18/ed-1.json", "date_issued": "1904-12-18", "title": {"url": "http://chroniclingamerica.loc.gov/lccn/sn90059523.json", "name": "The Saint Paul globe."}}, {"url": "http://chroniclingamerica.loc.gov/lccn/sn90059523/1904-12-19/ed-1.json", "date_issued": "1904-12-19", "title": {"url": "http://chroniclingamerica.loc.gov/lccn/sn90059523.json", "name": "The Saint Paul globe."}}, {"url": "http://chroniclingamerica.loc.gov/lccn/sn90059523/1904-12-20/ed-1.json", "date_issued": "1904-12-20", "title": {"url": "http://chroniclingamerica.loc.gov/lccn/sn90059523.json", "name": "The Saint Paul globe."}}, {"url": "http://chroniclingamerica.loc.gov/lccn/sn90059523/1904-12-21/ed-1.json", "date_issued": "1904-12-21", "title": {"url": "http://chroniclingamerica.loc.gov/lccn/sn90059523.json", "name": "The Saint Paul globe."}}, {"url": "http://chroniclingamerica.loc.gov/lccn/sn90059523/1904-12-22/ed-1.json", "date_issued": "1904-12-22", "title": {"url": "http://chroniclingamerica.loc.gov/lccn/sn90059523.json", "name": "The Saint Paul globe."}}, {"url": "http://chroniclingamerica.loc.gov/lccn/sn90059523/1904-12-23/ed-1.json", "date_issued": "1904-12-23", "title": {"url": "http://chroniclingamerica.loc.gov/lccn/sn90059523.json", "name": "The Saint Paul globe."}}, {"url": "http://chroniclingamerica.loc.gov/lccn/sn90059523/1904-12-24/ed-1.json", "date_issued": "1904-12-24", "title": {"url": "http://chroniclingamerica.loc.gov/lccn/sn90059523.json", "name": "The Saint Paul globe."}}, {"url": "http://chroniclingamerica.loc.gov/lccn/sn90059523/1904-12-25/ed-1.json", "date_issued": "1904-12-25", "title": {"url": "http://chroniclingamerica.loc.gov/lccn/sn90059523.json", "name": "The Saint Paul globe."}}, {"url": "http://chroniclingamerica.loc.gov/lccn/sn90059523/1904-12-26/ed-1.json", "date_issued": "1904-12-26", "title": {"url": "http://chroniclingamerica.loc.gov/lccn/sn90059523.json", "name": "The Saint Paul globe."}}, {"url": "http://chroniclingamerica.loc.gov/lccn/sn90059523/1904-12-27/ed-1.json", "date_issued": "1904-12-27", "title": {"url": "http://chroniclingamerica.loc.gov/lccn/sn90059523.json", "name": "The Saint Paul globe."}}, {"url": "http://chroniclingamerica.loc.gov/lccn/sn90059523/1904-12-28/ed-1.json", "date_issued": "1904-12-28", "title": {"url": "http://chroniclingamerica.loc.gov/lccn/sn90059523.json", "name": "The Saint Paul globe."}}, {"url": "http://chroniclingamerica.loc.gov/lccn/sn90059523/1904-12-29/ed-1.json", "date_issued": "1904-12-29", "title": {"url": "http://chroniclingamerica.loc.gov/lccn/sn90059523.json", "name": "The Saint Paul globe."}}, {"url": "http://chroniclingamerica.loc.gov/lccn/sn90059523/1904-12-30/ed-1.json", "date_issued": "1904-12-30", "title": {"url": "http://chroniclingamerica.loc.gov/lccn/sn90059523.json", "name": "The Saint Paul globe."}}, {"url": "http://chroniclingamerica.loc.gov/lccn/sn90059523/1904-12-31/ed-1.json", "date_issued": "1904-12-31", "title": {"url": "http://chroniclingamerica.loc.gov/lccn/sn90059523.json", "name": "The Saint Paul globe."}}, {"url": "http://chroniclingamerica.loc.gov/lccn/sn90059523/1905-02-01/ed-1.json", "date_issued": "1905-02-01", "title": {"url": "http://chroniclingamerica.loc.gov/lccn/sn90059523.json", "name": "The Saint Paul globe."}}, {"url": "http://chroniclingamerica.loc.gov/lccn/sn90059523/1905-02-02/ed-1.json", "date_issued": "1905-02-02", "title": {"url": "http://chroniclingamerica.loc.gov/lccn/sn90059523.json", "name": "The Saint Paul globe."}}, {"url": "http://chroniclingamerica.loc.gov/lccn/sn90059523/1905-02-03/ed-1.json", "date_issued": "1905-02-03", "title": {"url": "http://chroniclingamerica.loc.gov/lccn/sn90059523.json", "name": "The Saint Paul globe."}}, {"url": "http://chroniclingamerica.loc.gov/lccn/sn90059523/1905-02-04/ed-1.json", "date_issued": "1905-02-04", "title": {"url": "http://chroniclingamerica.loc.gov/lccn/sn90059523.json", "name": "The Saint Paul globe."}}, {"url": "http://chroniclingamerica.loc.gov/lccn/sn90059523/1905-02-05/ed-1.json", "date_issued": "1905-02-05", "title": {"url": "http://chroniclingamerica.loc.gov/lccn/sn90059523.json", "name": "The Saint Paul globe."}}, {"url": "http://chroniclingamerica.loc.gov/lccn/sn90059523/1905-02-06/ed-1.json", "date_issued": "1905-02-06", "title": {"url": "http://chroniclingamerica.loc.gov/lccn/sn90059523.json", "name": "The Saint Paul globe."}}, {"url": "http://chroniclingamerica.loc.gov/lccn/sn90059523/1905-02-07/ed-1.json", "date_issued": "1905-02-07", "title": {"url": "http://chroniclingamerica.loc.gov/lccn/sn90059523.json", "name": "The Saint Paul globe."}}, {"url": "http://chroniclingamerica.loc.gov/lccn/sn90059523/1905-02-08/ed-1.json", "date_issued": "1905-02-08", "title": {"url": "http://chroniclingamerica.loc.gov/lccn/sn90059523.json", "name": "The Saint Paul globe."}}, {"url": "http://chroniclingamerica.loc.gov/lccn/sn90059523/1905-02-09/ed-1.json", "date_issued": "1905-02-09", "title": {"url": "http://chroniclingamerica.loc.gov/lccn/sn90059523.json", "name": "The Saint Paul globe."}}, {"url": "http://chroniclingamerica.loc.gov/lccn/sn90059523/1905-02-10/ed-1.json", "date_issued": "1905-02-10", "title": {"url": "http://chroniclingamerica.loc.gov/lccn/sn90059523.json", "name": "The Saint Paul globe."}}, {"url": "http://chroniclingamerica.loc.gov/lccn/sn90059523/1905-02-11/ed-1.json", "date_issued": "1905-02-11", "title": {"url": "http://chroniclingamerica.loc.gov/lccn/sn90059523.json", "name": "The Saint Paul globe."}}, {"url": "http://chroniclingamerica.loc.gov/lccn/sn90059523/1905-02-12/ed-1.json", "date_issued": "1905-02-12", "title": {"url": "http://chroniclingamerica.loc.gov/lccn/sn90059523.json", "name": "The Saint Paul globe."}}, {"url": "http://chroniclingamerica.loc.gov/lccn/sn90059523/1905-02-13/ed-1.json", "date_issued": "1905-02-13", "title": {"url": "http://chroniclingamerica.loc.gov/lccn/sn90059523.json", "name": "The Saint Paul globe."}}, {"url": "http://chroniclingamerica.loc.gov/lccn/sn90059523/1905-02-14/ed-1.json", "date_issued": "1905-02-14", "title": {"url": "http://chroniclingamerica.loc.gov/lccn/sn90059523.json", "name": "The Saint Paul globe."}}, {"url": "http://chroniclingamerica.loc.gov/lccn/sn90059523/1905-02-15/ed-1.json", "date_issued": "1905-02-15", "title": {"url": "http://chroniclingamerica.loc.gov/lccn/sn90059523.json", "name": "The Saint Paul globe."}}, {"url": "http://chroniclingamerica.loc.gov/lccn/sn90059523/1905-02-16/ed-1.json", "date_issued": "1905-02-16", "title": {"url": "http://chroniclingamerica.loc.gov/lccn/sn90059523.json", "name": "The Saint Paul globe."}}, {"url": "http://chroniclingamerica.loc.gov/lccn/sn90059523/1905-02-17/ed-1.json", "date_issued": "1905-02-17", "title": {"url": "http://chroniclingamerica.loc.gov/lccn/sn90059523.json", "name": "The Saint Paul globe."}}, {"url": "http://chroniclingamerica.loc.gov/lccn/sn90059523/1905-02-18/ed-1.json", "date_issued": "1905-02-18", "title": {"url": "http://chroniclingamerica.loc.gov/lccn/sn90059523.json", "name": "The Saint Paul globe."}}, {"url": "http://chroniclingamerica.loc.gov/lccn/sn90059523/1905-02-19/ed-1.json", "date_issued": "1905-02-19", "title": {"url": "http://chroniclingamerica.loc.gov/lccn/sn90059523.json", "name": "The Saint Paul globe."}}, {"url": "http://chroniclingamerica.loc.gov/lccn/sn90059523/1905-02-20/ed-1.json", "date_issued": "1905-02-20", "title": {"url": "http://chroniclingamerica.loc.gov/lccn/sn90059523.json", "name": "The Saint Paul globe."}}, {"url": "http://chroniclingamerica.loc.gov/lccn/sn90059523/1905-02-21/ed-1.json", "date_issued": "1905-02-21", "title": {"url": "http://chroniclingamerica.loc.gov/lccn/sn90059523.json", "name": "The Saint Paul globe."}}, {"url": "http://chroniclingamerica.loc.gov/lccn/sn90059523/1905-02-22/ed-1.json", "date_issued": "1905-02-22", "title": {"url": "http://chroniclingamerica.loc.gov/lccn/sn90059523.json", "name": "The Saint Paul globe."}}, {"url": "http://chroniclingamerica.loc.gov/lccn/sn90059523/1905-02-23/ed-1.json", "date_issued": "1905-02-23", "title": {"url": "http://chroniclingamerica.loc.gov/lccn/sn90059523.json", "name": "The Saint Paul globe."}}, {"url": "http://chroniclingamerica.loc.gov/lccn/sn90059523/1905-02-24/ed-1.json", "date_issued": "1905-02-24", "title": {"url": "http://chroniclingamerica.loc.gov/lccn/sn90059523.json", "name": "The Saint Paul globe."}}, {"url": "http://chroniclingamerica.loc.gov/lccn/sn90059523/1905-02-25/ed-1.json", "date_issued": "1905-02-25", "title": {"url": "http://chroniclingamerica.loc.gov/lccn/sn90059523.json", "name": "The Saint Paul globe."}}, {"url": "http://chroniclingamerica.loc.gov/lccn/sn90059523/1905-02-26/ed-1.json", "date_issued": "1905-02-26", "title": {"url": "http://chroniclingamerica.loc.gov/lccn/sn90059523.json", "name": "The Saint Paul globe."}}, {"url": "http://chroniclingamerica.loc.gov/lccn/sn90059523/1905-02-27/ed-1.json", "date_issued": "1905-02-27", "title": {"url": "http://chroniclingamerica.loc.gov/lccn/sn90059523.json", "name": "The Saint Paul globe."}}, {"url": "http://chroniclingamerica.loc.gov/lccn/sn90059523/1905-02-28/ed-1.json", "date_issued": "1905-02-28", "title": {"url": "http://chroniclingamerica.loc.gov/lccn/sn90059523.json", "name": "The Saint Paul globe."}}]}